{"authorDailyContributionsMap":{"itayrefaely":[{"date":"2023-08-21","commitResults":[{"hash":"51a8a577a6b8acadf363cddff9758721c473230c","isMergeCommit":false,"messageTitle":"greeting","messageBody":"","tags":["Level-0"],"fileTypesAndContributionMap":{"java":{"insertions":15,"deletions":0}}}]},{"date":"2023-09-06","commitResults":[{"hash":"83e047ec71d3b7f9cff8458a62feac3d81730d56","isMergeCommit":false,"messageTitle":"Echo","messageBody":"","fileTypesAndContributionMap":{"java":{"insertions":0,"deletions":10}}},{"hash":"6a9b286bbc03d41b17edd950103ecad225a91bd8","isMergeCommit":false,"messageTitle":"Echo","messageBody":"","tags":["Level-1"],"fileTypesAndContributionMap":{"java":{"insertions":17,"deletions":0}}},{"hash":"cd90561b3ee50472e9cb38faf38bab8451a820c5","isMergeCommit":false,"messageTitle":"Add list","messageBody":"","tags":["Level-2"],"fileTypesAndContributionMap":{"java":{"insertions":21,"deletions":5}}},{"hash":"11178b3ba92b52987418abed5ca3400ee25bdbfd","isMergeCommit":false,"messageTitle":"Add mark/unmark","messageBody":"","tags":["Level-3"],"fileTypesAndContributionMap":{"java":{"insertions":50,"deletions":10}}}]},{"date":"2023-09-07","commitResults":[{"hash":"3824860dc28174ea0cd4a9abc7bd5cc002bf3b40","isMergeCommit":false,"messageTitle":"week 4","messageBody":"","tags":["Level-4"],"fileTypesAndContributionMap":{"java":{"insertions":52,"deletions":0}}},{"hash":"a2a782e4fdc514d5578b7ae83f0ea05905f56941","isMergeCommit":false,"messageTitle":"FIle name change","messageBody":"","fileTypesAndContributionMap":{"java":{"insertions":126,"deletions":62}}},{"hash":"a3ae62561b1ac8ceda00473e406bff0a444fefcd","isMergeCommit":false,"messageTitle":"input","messageBody":"","fileTypesAndContributionMap":{"txt":{"insertions":10,"deletions":0}}},{"hash":"8fda5d50a26710bb9cf894a424b5632e3ab5dcaf","isMergeCommit":false,"messageTitle":"file name change","messageBody":"","fileTypesAndContributionMap":{"java":{"insertions":152,"deletions":0}}},{"hash":"125560a12961b9f0baa84bc6c2bf67a40e1fe8fc","isMergeCommit":false,"messageTitle":"Delete src/main/java/Duke.java","messageBody":"","fileTypesAndContributionMap":{"java":{"insertions":0,"deletions":152}}},{"hash":"4f696510441354b8a94a5e6eaec7d1873f30b36e","isMergeCommit":false,"messageTitle":"Rename itay.java to Itay.java","messageBody":"","fileTypesAndContributionMap":{"java":{"insertions":1,"deletions":1}}}]},{"date":"2023-09-13","commitResults":[{"hash":"ac9e1e1b9dbc275bac3bc1832aaaca46944e7046","isMergeCommit":false,"messageTitle":"add DukeException class","messageBody":"","fileTypesAndContributionMap":{"java":{"insertions":14,"deletions":0}}},{"hash":"7dff1f961a46b1ba323bac6c44986b0c4f051a8d","isMergeCommit":false,"messageTitle":"Level-5","messageBody":"","tags":["A-Exceptions"],"fileTypesAndContributionMap":{"java":{"insertions":79,"deletions":206}}},{"hash":"e9b739d7653f6974e6a9424a6352a7f100326527","isMergeCommit":true,"messageTitle":"Merge branch \u0027branch-Level-5\u0027","messageBody":"Level-5\n","tags":["Level-5"],"fileTypesAndContributionMap":{}},{"hash":"656b0dbdddba8361201f367191d83b4fd1fd5e45","isMergeCommit":true,"messageTitle":"Merge remote-tracking branch \u0027origin/master\u0027","messageBody":"","fileTypesAndContributionMap":{}},{"hash":"1ee62b161225baac52209862fdbc57801b94e52c","isMergeCommit":false,"messageTitle":"A-Packages","messageBody":"","fileTypesAndContributionMap":{"java":{"insertions":5,"deletions":0}}},{"hash":"9131414083d930c991d7ffb9c3dbdf53ceb4f39a","isMergeCommit":true,"messageTitle":"Merge branch \u0027branch-A-Packages\u0027","messageBody":"","tags":["A-Packages"],"fileTypesAndContributionMap":{}},{"hash":"b57d0f8ab6aa4072b6d44ab1a8b63af6c15498be","isMergeCommit":false,"messageTitle":"A-Exceptions","messageBody":"","fileTypesAndContributionMap":{"java":{"insertions":0,"deletions":1}}}]},{"date":"2023-09-17","commitResults":[{"hash":"44b51f68ecdb0f5750436beb1b288f6080880eab","isMergeCommit":false,"messageTitle":"Quality modifications","messageBody":"","fileTypesAndContributionMap":{"java":{"insertions":22,"deletions":34}}},{"hash":"7dcbebbc32db4cd9c7072d9f59c599d666987f51","isMergeCommit":false,"messageTitle":"A-Collections","messageBody":"","tags":["A-Collections"],"fileTypesAndContributionMap":{"java":{"insertions":15,"deletions":14}}},{"hash":"7958848c9861afada1b05d2377874b82a1439810","isMergeCommit":false,"messageTitle":"Level-6","messageBody":"","fileTypesAndContributionMap":{"java":{"insertions":32,"deletions":15}}},{"hash":"c4ad597a385328d306769b6ce87ec0d9078dc871","isMergeCommit":true,"messageTitle":"Merge branch \u0027branch-Level-6\u0027","messageBody":"","tags":["Level-6"],"fileTypesAndContributionMap":{}},{"hash":"4ba5ceb95f6cc39e4aee80658a70e7348bd6a2d3","isMergeCommit":false,"messageTitle":"Level-7","messageBody":"","fileTypesAndContributionMap":{"txt":{"insertions":0,"deletions":0},"java":{"insertions":129,"deletions":11}}},{"hash":"8148969686a6782f3ed46003e18a15b6173896ae","isMergeCommit":true,"messageTitle":"Merge branch \u0027branch-Level-7\u0027","messageBody":"","tags":["Level-7"],"fileTypesAndContributionMap":{}}]},{"date":"2023-09-22","commitResults":[{"hash":"667907fed4f9c8a2fb338aef52676e7a35ab341e","isMergeCommit":false,"messageTitle":"A-More-OOP","messageBody":"","fileTypesAndContributionMap":{"java":{"insertions":281,"deletions":160}}},{"hash":"14c9949fa3f60403471c0b304e37fd7a294c960f","isMergeCommit":true,"messageTitle":"Merge branch \u0027branch-A-MoreOOP\u0027","messageBody":"","tags":["A-MoreOOP"],"fileTypesAndContributionMap":{}}]},{"date":"2023-09-23","commitResults":[{"hash":"89744627a28e561583d382349b74f5fe6be5d90f","isMergeCommit":false,"messageTitle":"Level-9","messageBody":"","fileTypesAndContributionMap":{"txt":{"insertions":3,"deletions":0},"java":{"insertions":146,"deletions":43}}},{"hash":"6bb96fc25700a13ee7143306bad237a503a3cf7d","isMergeCommit":false,"messageTitle":"Level-9","messageBody":"","fileTypesAndContributionMap":{"java":{"insertions":6,"deletions":6}}},{"hash":"b636a027b66462cdf63c182111a24fc32d02ce88","isMergeCommit":false,"messageTitle":"JavaDoc","messageBody":"","fileTypesAndContributionMap":{"java":{"insertions":192,"deletions":11}}},{"hash":"410f8214cb99e27b20425b416fda20e9edcef5bb","isMergeCommit":true,"messageTitle":"Merge pull request #1 from itayrefaely/branch-A-JavaDoc","messageBody":"JavaDoc","tags":["A-JavaDoc"],"fileTypesAndContributionMap":{}},{"hash":"c497d94c02ea871313b0bb9d19d383cace65bdc4","isMergeCommit":true,"messageTitle":"resolve conflicts","messageBody":"","fileTypesAndContributionMap":{}},{"hash":"b6a3757e7935e9541628e3dcb58566218a6b5b5f","isMergeCommit":true,"messageTitle":"Merge pull request #2 from itayrefaely/branch-Level-9","messageBody":"Branch level 9","tags":["Level-9"],"fileTypesAndContributionMap":{}},{"hash":"1d5655e964b416c3b96e1a12010c3429c4d7408c","isMergeCommit":false,"messageTitle":"Final tweeks","messageBody":"","fileTypesAndContributionMap":{"java":{"insertions":17,"deletions":0}}}]},{"date":"2023-09-25","commitResults":[{"hash":"a8a0ec6fa73bd985b6668019323c8f04af0e4ce7","isMergeCommit":false,"messageTitle":"More tweeks","messageBody":"","fileTypesAndContributionMap":{"txt":{"insertions":1,"deletions":1},"java":{"insertions":44,"deletions":44}}},{"hash":"0cfe3c92af986908ea60811056cc2ec366dbe430","isMergeCommit":false,"messageTitle":"Even more tweeks","messageBody":"","fileTypesAndContributionMap":{"java":{"insertions":2,"deletions":0}}},{"hash":"cb04de348c546ca181b4127706f9344be0752b0a","isMergeCommit":false,"messageTitle":"Update README.md","messageBody":"","fileTypesAndContributionMap":{"md":{"insertions":259,"deletions":24}}},{"hash":"3a827da424ac720b4b860d7f5970954dfbb19552","isMergeCommit":false,"messageTitle":"Update README.md","messageBody":"Undoing previous mistake","fileTypesAndContributionMap":{"md":{"insertions":24,"deletions":259}}},{"hash":"7f40e1ea68ec41bcd65f39f4b0e4e3145eaa3206","isMergeCommit":false,"messageTitle":"Update README.md","messageBody":"","tags":["A-UserGuide","A-Release"],"fileTypesAndContributionMap":{"md":{"insertions":240,"deletions":10}}}]},{"date":"2023-10-10","commitResults":[{"hash":"fc38af7a377011c4d91856fa2cf08ca74f3781eb","isMergeCommit":false,"messageTitle":"Update README.md","messageBody":"","fileTypesAndContributionMap":{"md":{"insertions":16,"deletions":20}}}]}]},"authorFileTypeContributionMap":{"itayrefaely":{"java":789,"md":250,"fxml":0,"sh":0,"bat":0,"gradle":0,"txt":13}},"authorContributionVariance":{"itayrefaely":28048.527},"authorDisplayNameMap":{"itayrefaely":"CS2113-W12-3 REFA..ITAY"}}
