[{"path":"src/main/java/ApplicationState.java","fileType":"java","lines":[{"lineNumber":1,"author":{"gitId":"Jonoans"},"content":"import java.util.ArrayList;","lastModifiedDate":"2023-08-27"},{"lineNumber":2,"author":{"gitId":"Jonoans"},"content":"import java.util.HashMap;","lastModifiedDate":"2023-09-04"},{"lineNumber":3,"author":{"gitId":"Jonoans"},"content":"","lastModifiedDate":"2023-08-27"},{"lineNumber":4,"author":{"gitId":"Jonoans"},"content":"public class ApplicationState {","lastModifiedDate":"2023-08-27"},{"lineNumber":5,"author":{"gitId":"Jonoans"},"content":"    private static ApplicationState appState \u003d null;","lastModifiedDate":"2023-08-27"},{"lineNumber":6,"author":{"gitId":"Jonoans"},"content":"    private final HashMap\u003cString, Object\u003e states \u003d new HashMap\u003c\u003e();","lastModifiedDate":"2023-09-04"},{"lineNumber":7,"author":{"gitId":"Jonoans"},"content":"    private final ArrayList\u003cTask\u003e TASKS \u003d new ArrayList\u003c\u003e();","lastModifiedDate":"2023-08-30"},{"lineNumber":8,"author":{"gitId":"Jonoans"},"content":"","lastModifiedDate":"2023-08-27"},{"lineNumber":9,"author":{"gitId":"Jonoans"},"content":"    private ApplicationState() {","lastModifiedDate":"2023-08-27"},{"lineNumber":10,"author":{"gitId":"Jonoans"},"content":"    }","lastModifiedDate":"2023-08-27"},{"lineNumber":11,"author":{"gitId":"Jonoans"},"content":"","lastModifiedDate":"2023-08-27"},{"lineNumber":12,"author":{"gitId":"Jonoans"},"content":"    public static ApplicationState getAppState() {","lastModifiedDate":"2023-08-27"},{"lineNumber":13,"author":{"gitId":"Jonoans"},"content":"        if (appState \u003d\u003d null) {","lastModifiedDate":"2023-08-30"},{"lineNumber":14,"author":{"gitId":"Jonoans"},"content":"            appState \u003d new ApplicationState();","lastModifiedDate":"2023-08-27"},{"lineNumber":15,"author":{"gitId":"Jonoans"},"content":"        }","lastModifiedDate":"2023-08-30"},{"lineNumber":16,"author":{"gitId":"Jonoans"},"content":"        return appState;","lastModifiedDate":"2023-08-27"},{"lineNumber":17,"author":{"gitId":"Jonoans"},"content":"    }","lastModifiedDate":"2023-08-27"},{"lineNumber":18,"author":{"gitId":"Jonoans"},"content":"","lastModifiedDate":"2023-08-27"},{"lineNumber":19,"author":{"gitId":"Jonoans"},"content":"    public Object getStateObject(String key) {","lastModifiedDate":"2023-09-04"},{"lineNumber":20,"author":{"gitId":"Jonoans"},"content":"        if (!states.containsKey(key)) {","lastModifiedDate":"2023-09-04"},{"lineNumber":21,"author":{"gitId":"Jonoans"},"content":"            return null;","lastModifiedDate":"2023-09-04"},{"lineNumber":22,"author":{"gitId":"Jonoans"},"content":"        }","lastModifiedDate":"2023-08-27"},{"lineNumber":23,"author":{"gitId":"Jonoans"},"content":"        return states.get(key);","lastModifiedDate":"2023-09-04"},{"lineNumber":24,"author":{"gitId":"Jonoans"},"content":"    }","lastModifiedDate":"2023-08-27"},{"lineNumber":25,"author":{"gitId":"Jonoans"},"content":"","lastModifiedDate":"2023-08-27"},{"lineNumber":26,"author":{"gitId":"Jonoans"},"content":"    public void setStateObject(String key, Object state) {","lastModifiedDate":"2023-09-04"},{"lineNumber":27,"author":{"gitId":"Jonoans"},"content":"        states.put(key, state);","lastModifiedDate":"2023-09-04"},{"lineNumber":28,"author":{"gitId":"Jonoans"},"content":"    }","lastModifiedDate":"2023-08-27"},{"lineNumber":29,"author":{"gitId":"Jonoans"},"content":"}","lastModifiedDate":"2023-08-27"}],"authorContributionMap":{"Jonoans":29}},{"path":"src/main/java/Command.java","fileType":"java","lines":[{"lineNumber":1,"author":{"gitId":"Jonoans"},"content":"import java.util.ArrayList;","lastModifiedDate":"2023-09-04"},{"lineNumber":2,"author":{"gitId":"Jonoans"},"content":"import java.util.HashMap;","lastModifiedDate":"2023-09-04"},{"lineNumber":3,"author":{"gitId":"Jonoans"},"content":"","lastModifiedDate":"2023-09-04"},{"lineNumber":4,"author":{"gitId":"Jonoans"},"content":"public class Command {","lastModifiedDate":"2023-09-04"},{"lineNumber":5,"author":{"gitId":"Jonoans"},"content":"    public static final String DEFAULT_ARGS \u003d \"_ARGS\";","lastModifiedDate":"2023-09-04"},{"lineNumber":6,"author":{"gitId":"Jonoans"},"content":"    private String originalCommand;","lastModifiedDate":"2023-09-04"},{"lineNumber":7,"author":{"gitId":"Jonoans"},"content":"    private String commandWord;","lastModifiedDate":"2023-09-04"},{"lineNumber":8,"author":{"gitId":"Jonoans"},"content":"    private String[] tokens;","lastModifiedDate":"2023-09-04"},{"lineNumber":9,"author":{"gitId":"Jonoans"},"content":"    private final HashMap\u003cString, String\u003e OPTIONS \u003d new HashMap\u003c\u003e();","lastModifiedDate":"2023-09-04"},{"lineNumber":10,"author":{"gitId":"Jonoans"},"content":"    private boolean isEmpty \u003d false;","lastModifiedDate":"2023-09-04"},{"lineNumber":11,"author":{"gitId":"Jonoans"},"content":"","lastModifiedDate":"2023-09-04"},{"lineNumber":12,"author":{"gitId":"Jonoans"},"content":"    public Command(String originalCommand) {","lastModifiedDate":"2023-09-04"},{"lineNumber":13,"author":{"gitId":"Jonoans"},"content":"        this.originalCommand \u003d originalCommand;","lastModifiedDate":"2023-09-04"},{"lineNumber":14,"author":{"gitId":"Jonoans"},"content":"        isEmpty \u003d originalCommand.isBlank();","lastModifiedDate":"2023-09-04"},{"lineNumber":15,"author":{"gitId":"Jonoans"},"content":"    }","lastModifiedDate":"2023-09-04"},{"lineNumber":16,"author":{"gitId":"Jonoans"},"content":"","lastModifiedDate":"2023-09-04"},{"lineNumber":17,"author":{"gitId":"Jonoans"},"content":"    public String getOriginalCommand() {","lastModifiedDate":"2023-09-04"},{"lineNumber":18,"author":{"gitId":"Jonoans"},"content":"        return originalCommand;","lastModifiedDate":"2023-09-04"},{"lineNumber":19,"author":{"gitId":"Jonoans"},"content":"    }","lastModifiedDate":"2023-09-04"},{"lineNumber":20,"author":{"gitId":"Jonoans"},"content":"","lastModifiedDate":"2023-09-04"},{"lineNumber":21,"author":{"gitId":"Jonoans"},"content":"    public String getCommandWord() {","lastModifiedDate":"2023-09-04"},{"lineNumber":22,"author":{"gitId":"Jonoans"},"content":"        return commandWord;","lastModifiedDate":"2023-09-04"},{"lineNumber":23,"author":{"gitId":"Jonoans"},"content":"    }","lastModifiedDate":"2023-09-04"},{"lineNumber":24,"author":{"gitId":"Jonoans"},"content":"","lastModifiedDate":"2023-09-04"},{"lineNumber":25,"author":{"gitId":"Jonoans"},"content":"    public String getArguments() {","lastModifiedDate":"2023-09-04"},{"lineNumber":26,"author":{"gitId":"Jonoans"},"content":"        return getOptions(DEFAULT_ARGS);","lastModifiedDate":"2023-09-04"},{"lineNumber":27,"author":{"gitId":"Jonoans"},"content":"    }","lastModifiedDate":"2023-09-04"},{"lineNumber":28,"author":{"gitId":"Jonoans"},"content":"","lastModifiedDate":"2023-09-04"},{"lineNumber":29,"author":{"gitId":"Jonoans"},"content":"    public String getOptions(String key) {","lastModifiedDate":"2023-09-04"},{"lineNumber":30,"author":{"gitId":"Jonoans"},"content":"        return OPTIONS.get(key.strip());","lastModifiedDate":"2023-09-04"},{"lineNumber":31,"author":{"gitId":"Jonoans"},"content":"    }","lastModifiedDate":"2023-09-04"},{"lineNumber":32,"author":{"gitId":"Jonoans"},"content":"","lastModifiedDate":"2023-09-04"},{"lineNumber":33,"author":{"gitId":"Jonoans"},"content":"    public boolean isEmpty() {","lastModifiedDate":"2023-09-04"},{"lineNumber":34,"author":{"gitId":"Jonoans"},"content":"        return isEmpty;","lastModifiedDate":"2023-09-04"},{"lineNumber":35,"author":{"gitId":"Jonoans"},"content":"    }","lastModifiedDate":"2023-09-04"},{"lineNumber":36,"author":{"gitId":"Jonoans"},"content":"","lastModifiedDate":"2023-09-04"},{"lineNumber":37,"author":{"gitId":"Jonoans"},"content":"    public void parse() {","lastModifiedDate":"2023-09-04"},{"lineNumber":38,"author":{"gitId":"Jonoans"},"content":"        tokens \u003d originalCommand.split(\" \");","lastModifiedDate":"2023-09-04"},{"lineNumber":39,"author":{"gitId":"Jonoans"},"content":"        if (tokens.length \u003e 0) {","lastModifiedDate":"2023-09-04"},{"lineNumber":40,"author":{"gitId":"Jonoans"},"content":"            commandWord \u003d tokens[0].strip().toLowerCase();","lastModifiedDate":"2023-09-04"},{"lineNumber":41,"author":{"gitId":"Jonoans"},"content":"        }","lastModifiedDate":"2023-09-04"},{"lineNumber":42,"author":{"gitId":"Jonoans"},"content":"        parseTokens();","lastModifiedDate":"2023-09-04"},{"lineNumber":43,"author":{"gitId":"Jonoans"},"content":"    }","lastModifiedDate":"2023-09-04"},{"lineNumber":44,"author":{"gitId":"Jonoans"},"content":"","lastModifiedDate":"2023-09-04"},{"lineNumber":45,"author":{"gitId":"Jonoans"},"content":"    public void parseTokens() {","lastModifiedDate":"2023-09-04"},{"lineNumber":46,"author":{"gitId":"Jonoans"},"content":"        if (isEmpty) {","lastModifiedDate":"2023-09-04"},{"lineNumber":47,"author":{"gitId":"Jonoans"},"content":"            return;","lastModifiedDate":"2023-09-04"},{"lineNumber":48,"author":{"gitId":"Jonoans"},"content":"        }","lastModifiedDate":"2023-09-04"},{"lineNumber":49,"author":{"gitId":"Jonoans"},"content":"","lastModifiedDate":"2023-09-04"},{"lineNumber":50,"author":{"gitId":"Jonoans"},"content":"        String optionKey \u003d DEFAULT_ARGS;","lastModifiedDate":"2023-09-04"},{"lineNumber":51,"author":{"gitId":"Jonoans"},"content":"        ArrayList\u003cString\u003e currentSet \u003d new ArrayList\u003c\u003e();","lastModifiedDate":"2023-09-04"},{"lineNumber":52,"author":{"gitId":"Jonoans"},"content":"        for (int i \u003d 1; i \u003c tokens.length; ++i) {","lastModifiedDate":"2023-09-04"},{"lineNumber":53,"author":{"gitId":"Jonoans"},"content":"            String token \u003d tokens[i];","lastModifiedDate":"2023-09-04"},{"lineNumber":54,"author":{"gitId":"Jonoans"},"content":"            if (token.startsWith(\"/\")) {","lastModifiedDate":"2023-09-04"},{"lineNumber":55,"author":{"gitId":"Jonoans"},"content":"                addOption(optionKey, String.join(\" \", currentSet));","lastModifiedDate":"2023-09-04"},{"lineNumber":56,"author":{"gitId":"Jonoans"},"content":"                optionKey \u003d token.substring(1);","lastModifiedDate":"2023-09-04"},{"lineNumber":57,"author":{"gitId":"Jonoans"},"content":"                currentSet.clear();","lastModifiedDate":"2023-09-04"},{"lineNumber":58,"author":{"gitId":"Jonoans"},"content":"            } else {","lastModifiedDate":"2023-09-04"},{"lineNumber":59,"author":{"gitId":"Jonoans"},"content":"                currentSet.add(token);","lastModifiedDate":"2023-09-04"},{"lineNumber":60,"author":{"gitId":"Jonoans"},"content":"            }","lastModifiedDate":"2023-09-04"},{"lineNumber":61,"author":{"gitId":"Jonoans"},"content":"        }","lastModifiedDate":"2023-09-04"},{"lineNumber":62,"author":{"gitId":"Jonoans"},"content":"","lastModifiedDate":"2023-09-04"},{"lineNumber":63,"author":{"gitId":"Jonoans"},"content":"        if (!currentSet.isEmpty()) {","lastModifiedDate":"2023-09-04"},{"lineNumber":64,"author":{"gitId":"Jonoans"},"content":"            addOption(optionKey, String.join(\" \", currentSet));","lastModifiedDate":"2023-09-04"},{"lineNumber":65,"author":{"gitId":"Jonoans"},"content":"        }","lastModifiedDate":"2023-09-04"},{"lineNumber":66,"author":{"gitId":"Jonoans"},"content":"    }","lastModifiedDate":"2023-09-04"},{"lineNumber":67,"author":{"gitId":"Jonoans"},"content":"","lastModifiedDate":"2023-09-04"},{"lineNumber":68,"author":{"gitId":"Jonoans"},"content":"    private void addOption(String key, String value) {","lastModifiedDate":"2023-09-04"},{"lineNumber":69,"author":{"gitId":"Jonoans"},"content":"        if (key.isBlank() || value.isBlank()) {","lastModifiedDate":"2023-09-04"},{"lineNumber":70,"author":{"gitId":"Jonoans"},"content":"            return;","lastModifiedDate":"2023-09-04"},{"lineNumber":71,"author":{"gitId":"Jonoans"},"content":"        }","lastModifiedDate":"2023-09-04"},{"lineNumber":72,"author":{"gitId":"Jonoans"},"content":"        OPTIONS.put(key.strip(), value.strip());","lastModifiedDate":"2023-09-04"},{"lineNumber":73,"author":{"gitId":"Jonoans"},"content":"    }","lastModifiedDate":"2023-09-04"},{"lineNumber":74,"author":{"gitId":"Jonoans"},"content":"}","lastModifiedDate":"2023-09-04"}],"authorContributionMap":{"Jonoans":74}},{"path":"src/main/java/Deadline.java","fileType":"java","lines":[{"lineNumber":1,"author":{"gitId":"Jonoans"},"content":"public class Deadline extends Task {","lastModifiedDate":"2023-09-04"},{"lineNumber":2,"author":{"gitId":"Jonoans"},"content":"    protected String by;","lastModifiedDate":"2023-09-04"},{"lineNumber":3,"author":{"gitId":"Jonoans"},"content":"","lastModifiedDate":"2023-09-04"},{"lineNumber":4,"author":{"gitId":"Jonoans"},"content":"    public Deadline(String name, String by) {","lastModifiedDate":"2023-09-04"},{"lineNumber":5,"author":{"gitId":"Jonoans"},"content":"        super(name);","lastModifiedDate":"2023-09-04"},{"lineNumber":6,"author":{"gitId":"Jonoans"},"content":"        this.by \u003d by;","lastModifiedDate":"2023-09-04"},{"lineNumber":7,"author":{"gitId":"Jonoans"},"content":"    }","lastModifiedDate":"2023-09-04"},{"lineNumber":8,"author":{"gitId":"Jonoans"},"content":"","lastModifiedDate":"2023-09-04"},{"lineNumber":9,"author":{"gitId":"Jonoans"},"content":"    @Override","lastModifiedDate":"2023-09-04"},{"lineNumber":10,"author":{"gitId":"Jonoans"},"content":"    public String toString() {","lastModifiedDate":"2023-09-04"},{"lineNumber":11,"author":{"gitId":"Jonoans"},"content":"        return String.format(\"[D]%s (by: %s)\", super.toString(), by);","lastModifiedDate":"2023-09-04"},{"lineNumber":12,"author":{"gitId":"Jonoans"},"content":"    }","lastModifiedDate":"2023-09-04"},{"lineNumber":13,"author":{"gitId":"Jonoans"},"content":"","lastModifiedDate":"2023-09-04"},{"lineNumber":14,"author":{"gitId":"Jonoans"},"content":"    @Override","lastModifiedDate":"2023-09-04"},{"lineNumber":15,"author":{"gitId":"Jonoans"},"content":"    public boolean isValid() {","lastModifiedDate":"2023-09-04"},{"lineNumber":16,"author":{"gitId":"Jonoans"},"content":"        return super.isValid() \u0026\u0026 by !\u003d null \u0026\u0026 !by.isBlank();","lastModifiedDate":"2023-09-04"},{"lineNumber":17,"author":{"gitId":"Jonoans"},"content":"    }","lastModifiedDate":"2023-09-04"},{"lineNumber":18,"author":{"gitId":"Jonoans"},"content":"}","lastModifiedDate":"2023-09-04"}],"authorContributionMap":{"Jonoans":18}},{"path":"src/main/java/Duke.java","fileType":"java","lines":[{"lineNumber":1,"author":{"gitId":"Jonoans"},"content":"import java.util.ArrayList;","lastModifiedDate":"2023-08-27"},{"lineNumber":2,"author":{"gitId":"Jonoans"},"content":"import java.util.HashMap;","lastModifiedDate":"2023-08-26"},{"lineNumber":3,"author":{"gitId":"Jonoans"},"content":"import java.util.Scanner;","lastModifiedDate":"2023-08-26"},{"lineNumber":4,"author":{"gitId":"Jonoans"},"content":"import java.util.function.Function;","lastModifiedDate":"2023-08-26"},{"lineNumber":5,"author":{"gitId":"Jonoans"},"content":"","lastModifiedDate":"2023-08-26"},{"lineNumber":6,"author":{"gitId":"-"},"content":"public class Duke {","lastModifiedDate":"2019-07-29"},{"lineNumber":7,"author":{"gitId":"Jonoans"},"content":"    private static boolean ended \u003d false;","lastModifiedDate":"2023-08-26"},{"lineNumber":8,"author":{"gitId":"Jonoans"},"content":"    private final static Scanner SCANNER \u003d new Scanner(System.in);","lastModifiedDate":"2023-08-30"},{"lineNumber":9,"author":{"gitId":"Jonoans"},"content":"    private final static HashMap\u003cString, Function\u003cCommand, Void\u003e\u003e COMMANDS \u003d new HashMap\u003c\u003e();","lastModifiedDate":"2023-09-04"},{"lineNumber":10,"author":{"gitId":"Jonoans"},"content":"","lastModifiedDate":"2023-08-26"},{"lineNumber":11,"author":{"gitId":"-"},"content":"    public static void main(String[] args) {","lastModifiedDate":"2019-07-29"},{"lineNumber":12,"author":{"gitId":"Jonoans"},"content":"        COMMANDS.put(\"bye\", (e) -\u003e bye());","lastModifiedDate":"2023-08-30"},{"lineNumber":13,"author":{"gitId":"Jonoans"},"content":"        COMMANDS.put(\"list\", (e) -\u003e listTasksFlow());","lastModifiedDate":"2023-08-30"},{"lineNumber":14,"author":{"gitId":"Jonoans"},"content":"        COMMANDS.put(\"mark\", Duke::markTaskFlow);","lastModifiedDate":"2023-08-30"},{"lineNumber":15,"author":{"gitId":"Jonoans"},"content":"        COMMANDS.put(\"unmark\", Duke::unmarkTaskFlow);","lastModifiedDate":"2023-08-30"},{"lineNumber":16,"author":{"gitId":"Jonoans"},"content":"        COMMANDS.put(\"deadline\", Duke::addTaskFlow);","lastModifiedDate":"2023-09-04"},{"lineNumber":17,"author":{"gitId":"Jonoans"},"content":"        COMMANDS.put(\"event\", Duke::addTaskFlow);","lastModifiedDate":"2023-09-04"},{"lineNumber":18,"author":{"gitId":"Jonoans"},"content":"        COMMANDS.put(\"todo\", Duke::addTaskFlow);","lastModifiedDate":"2023-09-04"},{"lineNumber":19,"author":{"gitId":"Jonoans"},"content":"","lastModifiedDate":"2023-08-27"},{"lineNumber":20,"author":{"gitId":"Jonoans"},"content":"        greet();","lastModifiedDate":"2023-08-26"},{"lineNumber":21,"author":{"gitId":"Jonoans"},"content":"        while (!ended) {","lastModifiedDate":"2023-08-26"},{"lineNumber":22,"author":{"gitId":"Jonoans"},"content":"            System.out.print(\"User: \");","lastModifiedDate":"2023-08-26"},{"lineNumber":23,"author":{"gitId":"Jonoans"},"content":"            String userInput \u003d getInput();","lastModifiedDate":"2023-08-26"},{"lineNumber":24,"author":{"gitId":"Jonoans"},"content":"            Command userCommand \u003d new Command(userInput);","lastModifiedDate":"2023-09-04"},{"lineNumber":25,"author":{"gitId":"Jonoans"},"content":"            userCommand.parse();","lastModifiedDate":"2023-09-04"},{"lineNumber":26,"author":{"gitId":"Jonoans"},"content":"","lastModifiedDate":"2023-08-27"},{"lineNumber":27,"author":{"gitId":"Jonoans"},"content":"            if (userCommand.isEmpty()) {","lastModifiedDate":"2023-09-04"},{"lineNumber":28,"author":{"gitId":"Jonoans"},"content":"                printWrapped(\"Please provide an input!\");","lastModifiedDate":"2023-08-30"},{"lineNumber":29,"author":{"gitId":"Jonoans"},"content":"                continue;","lastModifiedDate":"2023-08-30"},{"lineNumber":30,"author":{"gitId":"Jonoans"},"content":"            }","lastModifiedDate":"2023-08-30"},{"lineNumber":31,"author":{"gitId":"Jonoans"},"content":"","lastModifiedDate":"2023-08-30"},{"lineNumber":32,"author":{"gitId":"Jonoans"},"content":"            Function\u003cCommand, Void\u003e command \u003d COMMANDS.get(userCommand.getCommandWord());","lastModifiedDate":"2023-09-04"},{"lineNumber":33,"author":{"gitId":"Jonoans"},"content":"            if (command \u003d\u003d null) {","lastModifiedDate":"2023-08-27"},{"lineNumber":34,"author":{"gitId":"Jonoans"},"content":"                printWrapped(\"Unknown command...\");","lastModifiedDate":"2023-09-04"},{"lineNumber":35,"author":{"gitId":"Jonoans"},"content":"                continue;","lastModifiedDate":"2023-08-27"},{"lineNumber":36,"author":{"gitId":"Jonoans"},"content":"            }","lastModifiedDate":"2023-08-27"},{"lineNumber":37,"author":{"gitId":"Jonoans"},"content":"","lastModifiedDate":"2023-08-27"},{"lineNumber":38,"author":{"gitId":"Jonoans"},"content":"            command.apply(userCommand);","lastModifiedDate":"2023-09-04"},{"lineNumber":39,"author":{"gitId":"Jonoans"},"content":"        }","lastModifiedDate":"2023-08-26"},{"lineNumber":40,"author":{"gitId":"Jonoans"},"content":"    }","lastModifiedDate":"2023-08-26"},{"lineNumber":41,"author":{"gitId":"Jonoans"},"content":"","lastModifiedDate":"2023-08-26"},{"lineNumber":42,"author":{"gitId":"Jonoans"},"content":"    public static String getInput() {","lastModifiedDate":"2023-08-26"},{"lineNumber":43,"author":{"gitId":"Jonoans"},"content":"        return SCANNER.nextLine();","lastModifiedDate":"2023-08-30"},{"lineNumber":44,"author":{"gitId":"Jonoans"},"content":"    }","lastModifiedDate":"2023-08-26"},{"lineNumber":45,"author":{"gitId":"Jonoans"},"content":"","lastModifiedDate":"2023-08-26"},{"lineNumber":46,"author":{"gitId":"Jonoans"},"content":"    public static Void addTaskFlow(Command command) {","lastModifiedDate":"2023-09-04"},{"lineNumber":47,"author":{"gitId":"Jonoans"},"content":"        Task newTask \u003d null;","lastModifiedDate":"2023-09-04"},{"lineNumber":48,"author":{"gitId":"Jonoans"},"content":"        switch (command.getCommandWord()) {","lastModifiedDate":"2023-09-04"},{"lineNumber":49,"author":{"gitId":"Jonoans"},"content":"        case \"deadline\":","lastModifiedDate":"2023-09-04"},{"lineNumber":50,"author":{"gitId":"Jonoans"},"content":"            newTask \u003d new Deadline(command.getArguments(), command.getOptions(\"by\"));","lastModifiedDate":"2023-09-04"},{"lineNumber":51,"author":{"gitId":"Jonoans"},"content":"            break;","lastModifiedDate":"2023-09-04"},{"lineNumber":52,"author":{"gitId":"Jonoans"},"content":"        case \"event\":","lastModifiedDate":"2023-09-04"},{"lineNumber":53,"author":{"gitId":"Jonoans"},"content":"            newTask \u003d new Event(command.getArguments(), command.getOptions(\"from\"), command.getOptions(\"to\"));","lastModifiedDate":"2023-09-04"},{"lineNumber":54,"author":{"gitId":"Jonoans"},"content":"            break;","lastModifiedDate":"2023-09-04"},{"lineNumber":55,"author":{"gitId":"Jonoans"},"content":"        case \"todo\":","lastModifiedDate":"2023-09-04"},{"lineNumber":56,"author":{"gitId":"Jonoans"},"content":"            newTask \u003d new Todo(command.getArguments());","lastModifiedDate":"2023-09-04"},{"lineNumber":57,"author":{"gitId":"Jonoans"},"content":"        }","lastModifiedDate":"2023-09-04"},{"lineNumber":58,"author":{"gitId":"Jonoans"},"content":"        if (newTask !\u003d null \u0026\u0026 newTask.isValid()) {","lastModifiedDate":"2023-09-04"},{"lineNumber":59,"author":{"gitId":"Jonoans"},"content":"            Task.addTask(newTask);","lastModifiedDate":"2023-09-04"},{"lineNumber":60,"author":{"gitId":"Jonoans"},"content":"            printAddedTask(newTask);","lastModifiedDate":"2023-09-04"},{"lineNumber":61,"author":{"gitId":"Jonoans"},"content":"        } else {","lastModifiedDate":"2023-09-04"},{"lineNumber":62,"author":{"gitId":"Jonoans"},"content":"            printWrapped(\"Failed to add new task...\");","lastModifiedDate":"2023-09-04"},{"lineNumber":63,"author":{"gitId":"Jonoans"},"content":"        }","lastModifiedDate":"2023-09-04"},{"lineNumber":64,"author":{"gitId":"Jonoans"},"content":"        return null;","lastModifiedDate":"2023-09-04"},{"lineNumber":65,"author":{"gitId":"Jonoans"},"content":"    }","lastModifiedDate":"2023-09-04"},{"lineNumber":66,"author":{"gitId":"Jonoans"},"content":"","lastModifiedDate":"2023-09-04"},{"lineNumber":67,"author":{"gitId":"Jonoans"},"content":"    private static void printAddedTask(Task task) {","lastModifiedDate":"2023-09-04"},{"lineNumber":68,"author":{"gitId":"Jonoans"},"content":"        int tasksCount \u003d Task.getTasks().size();","lastModifiedDate":"2023-09-04"},{"lineNumber":69,"author":{"gitId":"Jonoans"},"content":"        String taskSummary \u003d String.format(","lastModifiedDate":"2023-09-04"},{"lineNumber":70,"author":{"gitId":"Jonoans"},"content":"                \"You now have %d %s in the list!\",","lastModifiedDate":"2023-09-04"},{"lineNumber":71,"author":{"gitId":"Jonoans"},"content":"                tasksCount,","lastModifiedDate":"2023-09-04"},{"lineNumber":72,"author":{"gitId":"Jonoans"},"content":"                (tasksCount \u003e 1) ? \"tasks\" : \"task\"","lastModifiedDate":"2023-09-04"},{"lineNumber":73,"author":{"gitId":"Jonoans"},"content":"        );","lastModifiedDate":"2023-09-04"},{"lineNumber":74,"author":{"gitId":"Jonoans"},"content":"","lastModifiedDate":"2023-09-04"},{"lineNumber":75,"author":{"gitId":"Jonoans"},"content":"        printWrapped(","lastModifiedDate":"2023-09-04"},{"lineNumber":76,"author":{"gitId":"Jonoans"},"content":"                \"Great! I\u0027ve added the following task:\\n\"","lastModifiedDate":"2023-09-04"},{"lineNumber":77,"author":{"gitId":"Jonoans"},"content":"                        + \"\\t\" + task + \"\\n\"","lastModifiedDate":"2023-09-04"},{"lineNumber":78,"author":{"gitId":"Jonoans"},"content":"                        + taskSummary","lastModifiedDate":"2023-09-04"},{"lineNumber":79,"author":{"gitId":"Jonoans"},"content":"        );","lastModifiedDate":"2023-09-04"},{"lineNumber":80,"author":{"gitId":"Jonoans"},"content":"    }","lastModifiedDate":"2023-08-27"},{"lineNumber":81,"author":{"gitId":"Jonoans"},"content":"","lastModifiedDate":"2023-08-27"},{"lineNumber":82,"author":{"gitId":"Jonoans"},"content":"    public static Void listTasksFlow() {","lastModifiedDate":"2023-08-27"},{"lineNumber":83,"author":{"gitId":"Jonoans"},"content":"        ArrayList\u003cTask\u003e tasks \u003d Task.getTasks();","lastModifiedDate":"2023-09-04"},{"lineNumber":84,"author":{"gitId":"Jonoans"},"content":"        int idx \u003d 1;","lastModifiedDate":"2023-08-27"},{"lineNumber":85,"author":{"gitId":"Jonoans"},"content":"        ProgramConstants.printSeparator();","lastModifiedDate":"2023-08-23"},{"lineNumber":86,"author":{"gitId":"Jonoans"},"content":"        for (Task task : tasks) {","lastModifiedDate":"2023-08-27"},{"lineNumber":87,"author":{"gitId":"Jonoans"},"content":"            System.out.printf(\"%d. %s\\n\", idx++, task);","lastModifiedDate":"2023-09-04"},{"lineNumber":88,"author":{"gitId":"Jonoans"},"content":"        }","lastModifiedDate":"2023-08-27"},{"lineNumber":89,"author":{"gitId":"Jonoans"},"content":"        ProgramConstants.printSeparator();","lastModifiedDate":"2023-08-23"},{"lineNumber":90,"author":{"gitId":"Jonoans"},"content":"        return null;","lastModifiedDate":"2023-08-26"},{"lineNumber":91,"author":{"gitId":"Jonoans"},"content":"    }","lastModifiedDate":"2023-08-26"},{"lineNumber":92,"author":{"gitId":"Jonoans"},"content":"","lastModifiedDate":"2023-08-26"},{"lineNumber":93,"author":{"gitId":"Jonoans"},"content":"    public static Void markTaskFlow(Command command) {","lastModifiedDate":"2023-09-04"},{"lineNumber":94,"author":{"gitId":"Jonoans"},"content":"        int taskNumber \u003d parsePositiveNumber(command.getArguments());","lastModifiedDate":"2023-09-04"},{"lineNumber":95,"author":{"gitId":"Jonoans"},"content":"        if (taskNumber \u003d\u003d -1) {","lastModifiedDate":"2023-08-27"},{"lineNumber":96,"author":{"gitId":"Jonoans"},"content":"            printWrapped(\"Failed to mark task as done...\");","lastModifiedDate":"2023-08-27"},{"lineNumber":97,"author":{"gitId":"Jonoans"},"content":"            return null;","lastModifiedDate":"2023-08-27"},{"lineNumber":98,"author":{"gitId":"Jonoans"},"content":"        }","lastModifiedDate":"2023-08-27"},{"lineNumber":99,"author":{"gitId":"Jonoans"},"content":"","lastModifiedDate":"2023-08-27"},{"lineNumber":100,"author":{"gitId":"Jonoans"},"content":"        Task task \u003d Task.getTask(--taskNumber);","lastModifiedDate":"2023-09-04"},{"lineNumber":101,"author":{"gitId":"Jonoans"},"content":"        if (task \u003d\u003d null) {","lastModifiedDate":"2023-08-27"},{"lineNumber":102,"author":{"gitId":"Jonoans"},"content":"            printWrapped(\"Failed to mark task as done...\");","lastModifiedDate":"2023-08-27"},{"lineNumber":103,"author":{"gitId":"Jonoans"},"content":"            return null;","lastModifiedDate":"2023-08-27"},{"lineNumber":104,"author":{"gitId":"Jonoans"},"content":"        }","lastModifiedDate":"2023-08-27"},{"lineNumber":105,"author":{"gitId":"Jonoans"},"content":"","lastModifiedDate":"2023-08-27"},{"lineNumber":106,"author":{"gitId":"Jonoans"},"content":"        task.markDone();","lastModifiedDate":"2023-08-27"},{"lineNumber":107,"author":{"gitId":"Jonoans"},"content":"        String printOut \u003d String.format(\"Nice I\u0027ve marked this task as done:\\n%s\", task);","lastModifiedDate":"2023-09-04"},{"lineNumber":108,"author":{"gitId":"Jonoans"},"content":"        printWrapped(printOut);","lastModifiedDate":"2023-08-27"},{"lineNumber":109,"author":{"gitId":"Jonoans"},"content":"        return null;","lastModifiedDate":"2023-08-27"},{"lineNumber":110,"author":{"gitId":"Jonoans"},"content":"    }","lastModifiedDate":"2023-08-27"},{"lineNumber":111,"author":{"gitId":"Jonoans"},"content":"","lastModifiedDate":"2023-08-27"},{"lineNumber":112,"author":{"gitId":"Jonoans"},"content":"    public static Void unmarkTaskFlow(Command command) {","lastModifiedDate":"2023-09-04"},{"lineNumber":113,"author":{"gitId":"Jonoans"},"content":"        int taskNumber \u003d parsePositiveNumber(command.getArguments());","lastModifiedDate":"2023-09-04"},{"lineNumber":114,"author":{"gitId":"Jonoans"},"content":"        if (taskNumber \u003d\u003d -1) {","lastModifiedDate":"2023-08-27"},{"lineNumber":115,"author":{"gitId":"Jonoans"},"content":"            printWrapped(\"Failed to mark task as undone...\");","lastModifiedDate":"2023-08-27"},{"lineNumber":116,"author":{"gitId":"Jonoans"},"content":"            return null;","lastModifiedDate":"2023-08-27"},{"lineNumber":117,"author":{"gitId":"Jonoans"},"content":"        }","lastModifiedDate":"2023-08-27"},{"lineNumber":118,"author":{"gitId":"Jonoans"},"content":"","lastModifiedDate":"2023-08-27"},{"lineNumber":119,"author":{"gitId":"Jonoans"},"content":"        Task task \u003d Task.getTask(--taskNumber);","lastModifiedDate":"2023-09-04"},{"lineNumber":120,"author":{"gitId":"Jonoans"},"content":"        if (task \u003d\u003d null) {","lastModifiedDate":"2023-08-27"},{"lineNumber":121,"author":{"gitId":"Jonoans"},"content":"            printWrapped(\"Failed to mark task as undone...\");","lastModifiedDate":"2023-08-27"},{"lineNumber":122,"author":{"gitId":"Jonoans"},"content":"            return null;","lastModifiedDate":"2023-08-27"},{"lineNumber":123,"author":{"gitId":"Jonoans"},"content":"        }","lastModifiedDate":"2023-08-27"},{"lineNumber":124,"author":{"gitId":"Jonoans"},"content":"","lastModifiedDate":"2023-08-27"},{"lineNumber":125,"author":{"gitId":"Jonoans"},"content":"        task.unmarkDone();","lastModifiedDate":"2023-08-27"},{"lineNumber":126,"author":{"gitId":"Jonoans"},"content":"        String printOut \u003d String.format(\"OK, I\u0027ve marked this task as not done yet:\\n%s\", task);","lastModifiedDate":"2023-09-04"},{"lineNumber":127,"author":{"gitId":"Jonoans"},"content":"        printWrapped(printOut);","lastModifiedDate":"2023-08-27"},{"lineNumber":128,"author":{"gitId":"Jonoans"},"content":"        return null;","lastModifiedDate":"2023-08-27"},{"lineNumber":129,"author":{"gitId":"Jonoans"},"content":"    }","lastModifiedDate":"2023-08-27"},{"lineNumber":130,"author":{"gitId":"Jonoans"},"content":"","lastModifiedDate":"2023-08-27"},{"lineNumber":131,"author":{"gitId":"Jonoans"},"content":"    public static int parsePositiveNumber(String number) {","lastModifiedDate":"2023-08-27"},{"lineNumber":132,"author":{"gitId":"Jonoans"},"content":"        int taskNumber \u003d -1;","lastModifiedDate":"2023-08-27"},{"lineNumber":133,"author":{"gitId":"Jonoans"},"content":"","lastModifiedDate":"2023-08-27"},{"lineNumber":134,"author":{"gitId":"Jonoans"},"content":"        try {","lastModifiedDate":"2023-08-27"},{"lineNumber":135,"author":{"gitId":"Jonoans"},"content":"            taskNumber \u003d Integer.parseInt(number);","lastModifiedDate":"2023-08-27"},{"lineNumber":136,"author":{"gitId":"Jonoans"},"content":"        } catch (NumberFormatException e) {","lastModifiedDate":"2023-08-27"},{"lineNumber":137,"author":{"gitId":"Jonoans"},"content":"            return taskNumber;","lastModifiedDate":"2023-08-27"},{"lineNumber":138,"author":{"gitId":"Jonoans"},"content":"        }","lastModifiedDate":"2023-08-27"},{"lineNumber":139,"author":{"gitId":"Jonoans"},"content":"","lastModifiedDate":"2023-08-27"},{"lineNumber":140,"author":{"gitId":"Jonoans"},"content":"        if (taskNumber \u003c\u003d 0) return -1;","lastModifiedDate":"2023-08-27"},{"lineNumber":141,"author":{"gitId":"Jonoans"},"content":"        return taskNumber;","lastModifiedDate":"2023-08-27"},{"lineNumber":142,"author":{"gitId":"Jonoans"},"content":"    }","lastModifiedDate":"2023-08-27"},{"lineNumber":143,"author":{"gitId":"Jonoans"},"content":"","lastModifiedDate":"2023-08-27"},{"lineNumber":144,"author":{"gitId":"Jonoans"},"content":"    public static void printWrapped(String printOut) {","lastModifiedDate":"2023-08-27"},{"lineNumber":145,"author":{"gitId":"Jonoans"},"content":"        ProgramConstants.printSeparator();","lastModifiedDate":"2023-08-27"},{"lineNumber":146,"author":{"gitId":"Jonoans"},"content":"        System.out.println(printOut);","lastModifiedDate":"2023-08-27"},{"lineNumber":147,"author":{"gitId":"Jonoans"},"content":"        ProgramConstants.printSeparator();","lastModifiedDate":"2023-08-27"},{"lineNumber":148,"author":{"gitId":"Jonoans"},"content":"    }","lastModifiedDate":"2023-08-27"},{"lineNumber":149,"author":{"gitId":"Jonoans"},"content":"","lastModifiedDate":"2023-08-27"},{"lineNumber":150,"author":{"gitId":"Jonoans"},"content":"    public static void greet() {","lastModifiedDate":"2023-08-26"},{"lineNumber":151,"author":{"gitId":"Jonoans"},"content":"        String greeting \u003d String.format(\"Hello I\u0027m %s\\n\", ProgramConstants.BOT_NAME) + \"What can I do for you?\";","lastModifiedDate":"2023-08-27"},{"lineNumber":152,"author":{"gitId":"Jonoans"},"content":"        printWrapped(greeting);","lastModifiedDate":"2023-08-26"},{"lineNumber":153,"author":{"gitId":"Jonoans"},"content":"    }","lastModifiedDate":"2023-08-26"},{"lineNumber":154,"author":{"gitId":"Jonoans"},"content":"","lastModifiedDate":"2023-08-26"},{"lineNumber":155,"author":{"gitId":"Jonoans"},"content":"    public static Void bye() {","lastModifiedDate":"2023-08-26"},{"lineNumber":156,"author":{"gitId":"Jonoans"},"content":"        printWrapped(\"Bye. Hope to see you again soon!\");","lastModifiedDate":"2023-08-26"},{"lineNumber":157,"author":{"gitId":"Jonoans"},"content":"        ended \u003d true;","lastModifiedDate":"2023-08-26"},{"lineNumber":158,"author":{"gitId":"Jonoans"},"content":"        return null;","lastModifiedDate":"2023-08-26"},{"lineNumber":159,"author":{"gitId":"-"},"content":"    }","lastModifiedDate":"2019-07-29"},{"lineNumber":160,"author":{"gitId":"-"},"content":"}","lastModifiedDate":"2019-07-29"}],"authorContributionMap":{"Jonoans":156,"-":4}},{"path":"src/main/java/Event.java","fileType":"java","lines":[{"lineNumber":1,"author":{"gitId":"Jonoans"},"content":"public class Event extends Task {","lastModifiedDate":"2023-09-04"},{"lineNumber":2,"author":{"gitId":"Jonoans"},"content":"    protected String from;","lastModifiedDate":"2023-09-04"},{"lineNumber":3,"author":{"gitId":"Jonoans"},"content":"    protected String to;","lastModifiedDate":"2023-09-04"},{"lineNumber":4,"author":{"gitId":"Jonoans"},"content":"","lastModifiedDate":"2023-09-04"},{"lineNumber":5,"author":{"gitId":"Jonoans"},"content":"    public Event(String name, String from, String to) {","lastModifiedDate":"2023-09-04"},{"lineNumber":6,"author":{"gitId":"Jonoans"},"content":"        super(name);","lastModifiedDate":"2023-09-04"},{"lineNumber":7,"author":{"gitId":"Jonoans"},"content":"        this.from \u003d from;","lastModifiedDate":"2023-09-04"},{"lineNumber":8,"author":{"gitId":"Jonoans"},"content":"        this.to \u003d to;","lastModifiedDate":"2023-09-04"},{"lineNumber":9,"author":{"gitId":"Jonoans"},"content":"    }","lastModifiedDate":"2023-09-04"},{"lineNumber":10,"author":{"gitId":"Jonoans"},"content":"","lastModifiedDate":"2023-09-04"},{"lineNumber":11,"author":{"gitId":"Jonoans"},"content":"    @Override","lastModifiedDate":"2023-09-04"},{"lineNumber":12,"author":{"gitId":"Jonoans"},"content":"    public String toString() {","lastModifiedDate":"2023-09-04"},{"lineNumber":13,"author":{"gitId":"Jonoans"},"content":"        return String.format(\"[E]%s (from: %s | to: %s)\", super.toString(), this.from, this.to);","lastModifiedDate":"2023-09-04"},{"lineNumber":14,"author":{"gitId":"Jonoans"},"content":"    }","lastModifiedDate":"2023-09-04"},{"lineNumber":15,"author":{"gitId":"Jonoans"},"content":"","lastModifiedDate":"2023-09-04"},{"lineNumber":16,"author":{"gitId":"Jonoans"},"content":"    @Override","lastModifiedDate":"2023-09-04"},{"lineNumber":17,"author":{"gitId":"Jonoans"},"content":"    public boolean isValid() {","lastModifiedDate":"2023-09-04"},{"lineNumber":18,"author":{"gitId":"Jonoans"},"content":"        return super.isValid() \u0026\u0026 from !\u003d null \u0026\u0026 !from.isBlank() \u0026\u0026 to !\u003d null \u0026\u0026 !to.isBlank();","lastModifiedDate":"2023-09-04"},{"lineNumber":19,"author":{"gitId":"Jonoans"},"content":"    }","lastModifiedDate":"2023-09-04"},{"lineNumber":20,"author":{"gitId":"Jonoans"},"content":"}","lastModifiedDate":"2023-09-04"}],"authorContributionMap":{"Jonoans":20}},{"path":"src/main/java/ProgramConstants.java","fileType":"java","lines":[{"lineNumber":1,"author":{"gitId":"Jonoans"},"content":"public final class ProgramConstants {","lastModifiedDate":"2023-08-23"},{"lineNumber":2,"author":{"gitId":"Jonoans"},"content":"    public static final String BOT_NAME \u003d \"DumbGPT\";","lastModifiedDate":"2023-08-23"},{"lineNumber":3,"author":{"gitId":"Jonoans"},"content":"    public static final String SEPARATOR \u003d \"____________________________________________________________\";","lastModifiedDate":"2023-08-23"},{"lineNumber":4,"author":{"gitId":"Jonoans"},"content":"","lastModifiedDate":"2023-08-23"},{"lineNumber":5,"author":{"gitId":"Jonoans"},"content":"    public static void printSeparator() {","lastModifiedDate":"2023-08-23"},{"lineNumber":6,"author":{"gitId":"Jonoans"},"content":"        System.out.println(SEPARATOR);","lastModifiedDate":"2023-08-23"},{"lineNumber":7,"author":{"gitId":"Jonoans"},"content":"    }","lastModifiedDate":"2023-08-23"},{"lineNumber":8,"author":{"gitId":"Jonoans"},"content":"","lastModifiedDate":"2023-08-23"},{"lineNumber":9,"author":{"gitId":"Jonoans"},"content":"    private ProgramConstants() {","lastModifiedDate":"2023-08-23"},{"lineNumber":10,"author":{"gitId":"Jonoans"},"content":"    }","lastModifiedDate":"2023-08-23"},{"lineNumber":11,"author":{"gitId":"Jonoans"},"content":"}","lastModifiedDate":"2023-08-23"}],"authorContributionMap":{"Jonoans":11}},{"path":"src/main/java/Task.java","fileType":"java","lines":[{"lineNumber":1,"author":{"gitId":"Jonoans"},"content":"import java.util.ArrayList;","lastModifiedDate":"2023-09-04"},{"lineNumber":2,"author":{"gitId":"Jonoans"},"content":"","lastModifiedDate":"2023-09-04"},{"lineNumber":3,"author":{"gitId":"Jonoans"},"content":"public class Task {","lastModifiedDate":"2023-08-27"},{"lineNumber":4,"author":{"gitId":"Jonoans"},"content":"    private final static String STATE_KEY \u003d \"Tasks\";","lastModifiedDate":"2023-09-04"},{"lineNumber":5,"author":{"gitId":"Jonoans"},"content":"    protected String name;","lastModifiedDate":"2023-08-27"},{"lineNumber":6,"author":{"gitId":"Jonoans"},"content":"    protected Boolean isDone;","lastModifiedDate":"2023-08-30"},{"lineNumber":7,"author":{"gitId":"Jonoans"},"content":"","lastModifiedDate":"2023-08-27"},{"lineNumber":8,"author":{"gitId":"Jonoans"},"content":"    public Task(String name) {","lastModifiedDate":"2023-08-27"},{"lineNumber":9,"author":{"gitId":"Jonoans"},"content":"        this.name \u003d name;","lastModifiedDate":"2023-08-27"},{"lineNumber":10,"author":{"gitId":"Jonoans"},"content":"        this.isDone \u003d false;","lastModifiedDate":"2023-08-30"},{"lineNumber":11,"author":{"gitId":"Jonoans"},"content":"    }","lastModifiedDate":"2023-08-27"},{"lineNumber":12,"author":{"gitId":"Jonoans"},"content":"","lastModifiedDate":"2023-08-27"},{"lineNumber":13,"author":{"gitId":"Jonoans"},"content":"    public String getName() {","lastModifiedDate":"2023-08-27"},{"lineNumber":14,"author":{"gitId":"Jonoans"},"content":"        return this.name;","lastModifiedDate":"2023-08-27"},{"lineNumber":15,"author":{"gitId":"Jonoans"},"content":"    }","lastModifiedDate":"2023-08-27"},{"lineNumber":16,"author":{"gitId":"Jonoans"},"content":"","lastModifiedDate":"2023-08-27"},{"lineNumber":17,"author":{"gitId":"Jonoans"},"content":"    public String getNameWithStatus() {","lastModifiedDate":"2023-08-27"},{"lineNumber":18,"author":{"gitId":"Jonoans"},"content":"        return String.format(\"[%s] %s\", this.isDone ? \"X\" : \" \", this.name);","lastModifiedDate":"2023-08-30"},{"lineNumber":19,"author":{"gitId":"Jonoans"},"content":"    }","lastModifiedDate":"2023-08-27"},{"lineNumber":20,"author":{"gitId":"Jonoans"},"content":"","lastModifiedDate":"2023-08-27"},{"lineNumber":21,"author":{"gitId":"Jonoans"},"content":"    public void markDone() {","lastModifiedDate":"2023-08-27"},{"lineNumber":22,"author":{"gitId":"Jonoans"},"content":"        this.isDone \u003d true;","lastModifiedDate":"2023-08-30"},{"lineNumber":23,"author":{"gitId":"Jonoans"},"content":"    }","lastModifiedDate":"2023-08-27"},{"lineNumber":24,"author":{"gitId":"Jonoans"},"content":"","lastModifiedDate":"2023-08-27"},{"lineNumber":25,"author":{"gitId":"Jonoans"},"content":"    public void unmarkDone() {","lastModifiedDate":"2023-08-27"},{"lineNumber":26,"author":{"gitId":"Jonoans"},"content":"        this.isDone \u003d false;","lastModifiedDate":"2023-08-30"},{"lineNumber":27,"author":{"gitId":"Jonoans"},"content":"    }","lastModifiedDate":"2023-08-27"},{"lineNumber":28,"author":{"gitId":"Jonoans"},"content":"","lastModifiedDate":"2023-09-04"},{"lineNumber":29,"author":{"gitId":"Jonoans"},"content":"    @Override","lastModifiedDate":"2023-09-04"},{"lineNumber":30,"author":{"gitId":"Jonoans"},"content":"    public String toString() {","lastModifiedDate":"2023-09-04"},{"lineNumber":31,"author":{"gitId":"Jonoans"},"content":"        return getNameWithStatus();","lastModifiedDate":"2023-09-04"},{"lineNumber":32,"author":{"gitId":"Jonoans"},"content":"    }","lastModifiedDate":"2023-09-04"},{"lineNumber":33,"author":{"gitId":"Jonoans"},"content":"","lastModifiedDate":"2023-09-04"},{"lineNumber":34,"author":{"gitId":"Jonoans"},"content":"    public boolean isValid() {","lastModifiedDate":"2023-09-04"},{"lineNumber":35,"author":{"gitId":"Jonoans"},"content":"        return name !\u003d null \u0026\u0026 !name.isBlank();","lastModifiedDate":"2023-09-04"},{"lineNumber":36,"author":{"gitId":"Jonoans"},"content":"    }","lastModifiedDate":"2023-09-04"},{"lineNumber":37,"author":{"gitId":"Jonoans"},"content":"","lastModifiedDate":"2023-09-04"},{"lineNumber":38,"author":{"gitId":"Jonoans"},"content":"    public static void addTask(Task task) {","lastModifiedDate":"2023-09-04"},{"lineNumber":39,"author":{"gitId":"Jonoans"},"content":"        ArrayList\u003cTask\u003e tasks \u003d getTasks();","lastModifiedDate":"2023-09-04"},{"lineNumber":40,"author":{"gitId":"Jonoans"},"content":"        tasks.add(task);","lastModifiedDate":"2023-09-04"},{"lineNumber":41,"author":{"gitId":"Jonoans"},"content":"    }","lastModifiedDate":"2023-09-04"},{"lineNumber":42,"author":{"gitId":"Jonoans"},"content":"","lastModifiedDate":"2023-09-04"},{"lineNumber":43,"author":{"gitId":"Jonoans"},"content":"    public static Task getTask(int pos) {","lastModifiedDate":"2023-09-04"},{"lineNumber":44,"author":{"gitId":"Jonoans"},"content":"        ArrayList\u003cTask\u003e tasks \u003d getTasks();","lastModifiedDate":"2023-09-04"},{"lineNumber":45,"author":{"gitId":"Jonoans"},"content":"        if (pos \u003c 0 || pos \u003e\u003d tasks.size()) {","lastModifiedDate":"2023-09-04"},{"lineNumber":46,"author":{"gitId":"Jonoans"},"content":"            return null;","lastModifiedDate":"2023-09-04"},{"lineNumber":47,"author":{"gitId":"Jonoans"},"content":"        }","lastModifiedDate":"2023-09-04"},{"lineNumber":48,"author":{"gitId":"Jonoans"},"content":"        return tasks.get(pos);","lastModifiedDate":"2023-09-04"},{"lineNumber":49,"author":{"gitId":"Jonoans"},"content":"    }","lastModifiedDate":"2023-09-04"},{"lineNumber":50,"author":{"gitId":"Jonoans"},"content":"","lastModifiedDate":"2023-09-04"},{"lineNumber":51,"author":{"gitId":"Jonoans"},"content":"    @SuppressWarnings(\"unchecked\")","lastModifiedDate":"2023-09-04"},{"lineNumber":52,"author":{"gitId":"Jonoans"},"content":"    public static ArrayList\u003cTask\u003e getTasks() {","lastModifiedDate":"2023-09-04"},{"lineNumber":53,"author":{"gitId":"Jonoans"},"content":"        ApplicationState appState \u003d ApplicationState.getAppState();","lastModifiedDate":"2023-09-04"},{"lineNumber":54,"author":{"gitId":"Jonoans"},"content":"        Object tasks \u003d appState.getStateObject(STATE_KEY);","lastModifiedDate":"2023-09-04"},{"lineNumber":55,"author":{"gitId":"Jonoans"},"content":"        if (tasks \u003d\u003d null) {","lastModifiedDate":"2023-09-04"},{"lineNumber":56,"author":{"gitId":"Jonoans"},"content":"            tasks \u003d new ArrayList\u003cTask\u003e();","lastModifiedDate":"2023-09-04"},{"lineNumber":57,"author":{"gitId":"Jonoans"},"content":"            appState.setStateObject(STATE_KEY, tasks);","lastModifiedDate":"2023-09-04"},{"lineNumber":58,"author":{"gitId":"Jonoans"},"content":"        }","lastModifiedDate":"2023-09-04"},{"lineNumber":59,"author":{"gitId":"Jonoans"},"content":"        return (ArrayList\u003cTask\u003e) tasks;","lastModifiedDate":"2023-09-04"},{"lineNumber":60,"author":{"gitId":"Jonoans"},"content":"    }","lastModifiedDate":"2023-09-04"},{"lineNumber":61,"author":{"gitId":"Jonoans"},"content":"}","lastModifiedDate":"2023-08-27"}],"authorContributionMap":{"Jonoans":61}},{"path":"src/main/java/Todo.java","fileType":"java","lines":[{"lineNumber":1,"author":{"gitId":"Jonoans"},"content":"public class Todo extends Task {","lastModifiedDate":"2023-09-04"},{"lineNumber":2,"author":{"gitId":"Jonoans"},"content":"    public Todo(String name) {","lastModifiedDate":"2023-09-04"},{"lineNumber":3,"author":{"gitId":"Jonoans"},"content":"        super(name);","lastModifiedDate":"2023-09-04"},{"lineNumber":4,"author":{"gitId":"Jonoans"},"content":"    }","lastModifiedDate":"2023-09-04"},{"lineNumber":5,"author":{"gitId":"Jonoans"},"content":"","lastModifiedDate":"2023-09-04"},{"lineNumber":6,"author":{"gitId":"Jonoans"},"content":"    @Override","lastModifiedDate":"2023-09-04"},{"lineNumber":7,"author":{"gitId":"Jonoans"},"content":"    public String toString() {","lastModifiedDate":"2023-09-04"},{"lineNumber":8,"author":{"gitId":"Jonoans"},"content":"        return String.format(\"[T]%s\", super.toString());","lastModifiedDate":"2023-09-04"},{"lineNumber":9,"author":{"gitId":"Jonoans"},"content":"    }","lastModifiedDate":"2023-09-04"},{"lineNumber":10,"author":{"gitId":"Jonoans"},"content":"}","lastModifiedDate":"2023-09-04"}],"authorContributionMap":{"Jonoans":10}},{"path":"text-ui-test/input.txt","fileType":"txt","lines":[{"lineNumber":1,"author":{"gitId":"Jonoans"},"content":"todo welcome","lastModifiedDate":"2023-09-04"},{"lineNumber":2,"author":{"gitId":"Jonoans"},"content":"todo hi","lastModifiedDate":"2023-09-04"},{"lineNumber":3,"author":{"gitId":"Jonoans"},"content":"deadline","lastModifiedDate":"2023-09-04"},{"lineNumber":4,"author":{"gitId":"Jonoans"},"content":"deadline deadline task","lastModifiedDate":"2023-09-04"},{"lineNumber":5,"author":{"gitId":"Jonoans"},"content":"deadline bad /by","lastModifiedDate":"2023-09-04"},{"lineNumber":6,"author":{"gitId":"Jonoans"},"content":"deadline deadline task /by Week 4","lastModifiedDate":"2023-09-04"},{"lineNumber":7,"author":{"gitId":"Jonoans"},"content":"event","lastModifiedDate":"2023-09-04"},{"lineNumber":8,"author":{"gitId":"Jonoans"},"content":"event an event","lastModifiedDate":"2023-09-04"},{"lineNumber":9,"author":{"gitId":"Jonoans"},"content":"event an event      /from","lastModifiedDate":"2023-09-04"},{"lineNumber":10,"author":{"gitId":"Jonoans"},"content":"event an event      /from A","lastModifiedDate":"2023-09-04"},{"lineNumber":11,"author":{"gitId":"Jonoans"},"content":"event an event      /from A /to","lastModifiedDate":"2023-09-04"},{"lineNumber":12,"author":{"gitId":"Jonoans"},"content":"event an event working     /from A /to Z","lastModifiedDate":"2023-09-04"},{"lineNumber":13,"author":{"gitId":"Jonoans"},"content":"list","lastModifiedDate":"2023-09-04"},{"lineNumber":14,"author":{"gitId":"Jonoans"},"content":"mark 0","lastModifiedDate":"2023-09-04"},{"lineNumber":15,"author":{"gitId":"Jonoans"},"content":"mark 5","lastModifiedDate":"2023-09-04"},{"lineNumber":16,"author":{"gitId":"Jonoans"},"content":"mark 1","lastModifiedDate":"2023-09-04"},{"lineNumber":17,"author":{"gitId":"Jonoans"},"content":"mark 4","lastModifiedDate":"2023-09-04"},{"lineNumber":18,"author":{"gitId":"Jonoans"},"content":"list","lastModifiedDate":"2023-09-04"},{"lineNumber":19,"author":{"gitId":"Jonoans"},"content":"bye","lastModifiedDate":"2023-09-04"}],"authorContributionMap":{"Jonoans":19}}]
