[{"path":"Main.java","fileType":"java","lines":[{"lineNumber":1,"author":{"gitId":"rohitcube"},"content":"public class Main {","lastModifiedDate":"2023-09-15"},{"lineNumber":2,"author":{"gitId":"rohitcube"},"content":"}","lastModifiedDate":"2023-09-15"}],"authorContributionMap":{"rohitcube":2}},{"path":"src/main/java/Dukey.java","fileType":"java","lines":[{"lineNumber":1,"author":{"gitId":"rohitcube"},"content":"","lastModifiedDate":"2023-09-15"},{"lineNumber":2,"author":{"gitId":"rohitcube"},"content":"","lastModifiedDate":"2023-09-15"},{"lineNumber":3,"author":{"gitId":"rohitcube"},"content":"import Tasks.*;","lastModifiedDate":"2023-09-15"},{"lineNumber":4,"author":{"gitId":"rohitcube"},"content":"import dukey.*;","lastModifiedDate":"2023-09-15"},{"lineNumber":5,"author":{"gitId":"rohitcube"},"content":"","lastModifiedDate":"2023-09-15"},{"lineNumber":6,"author":{"gitId":"rohitcube"},"content":"import java.util.ArrayList;","lastModifiedDate":"2023-09-07"},{"lineNumber":7,"author":{"gitId":"rohitcube"},"content":"import java.util.Scanner;","lastModifiedDate":"2023-09-07"},{"lineNumber":8,"author":{"gitId":"rohitcube"},"content":"","lastModifiedDate":"2023-09-07"},{"lineNumber":9,"author":{"gitId":"rohitcube"},"content":"public class Dukey {","lastModifiedDate":"2023-09-07"},{"lineNumber":10,"author":{"gitId":"rohitcube"},"content":"    private static void addTodo(String line, ArrayList\u003cTask\u003e tasks) {","lastModifiedDate":"2023-09-08"},{"lineNumber":11,"author":{"gitId":"rohitcube"},"content":"        String[] words \u003d line.split(\" \");","lastModifiedDate":"2023-09-15"},{"lineNumber":12,"author":{"gitId":"rohitcube"},"content":"        String description \u003d null;","lastModifiedDate":"2023-09-15"},{"lineNumber":13,"author":{"gitId":"rohitcube"},"content":"        try {","lastModifiedDate":"2023-09-15"},{"lineNumber":14,"author":{"gitId":"rohitcube"},"content":"            description \u003d words[1];","lastModifiedDate":"2023-09-15"},{"lineNumber":15,"author":{"gitId":"rohitcube"},"content":"            tasks.add(new Todo(description));","lastModifiedDate":"2023-09-08"},{"lineNumber":16,"author":{"gitId":"rohitcube"},"content":"            tasks.get(tasks.size() - 1).printNewTask();","lastModifiedDate":"2023-09-08"},{"lineNumber":17,"author":{"gitId":"rohitcube"},"content":"        } catch(IndexOutOfBoundsException e) {","lastModifiedDate":"2023-09-15"},{"lineNumber":18,"author":{"gitId":"rohitcube"},"content":"            System.out.println(\"_____________________________________________________\");","lastModifiedDate":"2023-09-15"},{"lineNumber":19,"author":{"gitId":"rohitcube"},"content":"            System.out.println(DukeyException.todoDescriptionError());","lastModifiedDate":"2023-09-15"},{"lineNumber":20,"author":{"gitId":"rohitcube"},"content":"            System.out.println(\"_____________________________________________________\");","lastModifiedDate":"2023-09-15"},{"lineNumber":21,"author":{"gitId":"rohitcube"},"content":"        }","lastModifiedDate":"2023-09-15"},{"lineNumber":22,"author":{"gitId":"rohitcube"},"content":"    }","lastModifiedDate":"2023-09-08"},{"lineNumber":23,"author":{"gitId":"rohitcube"},"content":"","lastModifiedDate":"2023-09-08"},{"lineNumber":24,"author":{"gitId":"rohitcube"},"content":"    private static void addEvent(String line, ArrayList\u003cTask\u003e tasks) {","lastModifiedDate":"2023-09-08"},{"lineNumber":25,"author":{"gitId":"rohitcube"},"content":"        int startIndexOfFrom \u003d line.indexOf(\"/from\");","lastModifiedDate":"2023-09-08"},{"lineNumber":26,"author":{"gitId":"rohitcube"},"content":"        int startIndexOfTo \u003d line.indexOf(\"/to\");","lastModifiedDate":"2023-09-08"},{"lineNumber":27,"author":{"gitId":"rohitcube"},"content":"        final int beginIndex \u003d 6;","lastModifiedDate":"2023-09-08"},{"lineNumber":28,"author":{"gitId":"rohitcube"},"content":"        try {","lastModifiedDate":"2023-09-15"},{"lineNumber":29,"author":{"gitId":"rohitcube"},"content":"        String from \u003d line.substring(startIndexOfFrom + 6, startIndexOfTo);","lastModifiedDate":"2023-09-08"},{"lineNumber":30,"author":{"gitId":"rohitcube"},"content":"        String to \u003d line.substring(startIndexOfTo + 4);","lastModifiedDate":"2023-09-08"},{"lineNumber":31,"author":{"gitId":"rohitcube"},"content":"        String description \u003d line.substring(beginIndex, startIndexOfFrom);","lastModifiedDate":"2023-09-08"},{"lineNumber":32,"author":{"gitId":"rohitcube"},"content":"        tasks.add(new Event(from, to, description));","lastModifiedDate":"2023-09-08"},{"lineNumber":33,"author":{"gitId":"rohitcube"},"content":"        tasks.get(tasks.size() - 1).printNewTask();","lastModifiedDate":"2023-09-08"},{"lineNumber":34,"author":{"gitId":"rohitcube"},"content":"        } catch(StringIndexOutOfBoundsException e) {","lastModifiedDate":"2023-09-15"},{"lineNumber":35,"author":{"gitId":"rohitcube"},"content":"            System.out.println(\"_____________________________________________________\");","lastModifiedDate":"2023-09-15"},{"lineNumber":36,"author":{"gitId":"rohitcube"},"content":"            System.out.println(DukeyException.EventFormatError());","lastModifiedDate":"2023-09-15"},{"lineNumber":37,"author":{"gitId":"rohitcube"},"content":"            System.out.println(\"_____________________________________________________\");","lastModifiedDate":"2023-09-15"},{"lineNumber":38,"author":{"gitId":"rohitcube"},"content":"        }","lastModifiedDate":"2023-09-15"},{"lineNumber":39,"author":{"gitId":"rohitcube"},"content":"    }","lastModifiedDate":"2023-09-08"},{"lineNumber":40,"author":{"gitId":"rohitcube"},"content":"","lastModifiedDate":"2023-09-08"},{"lineNumber":41,"author":{"gitId":"rohitcube"},"content":"    private static void addDeadline(String line, ArrayList\u003cTask\u003e tasks) {","lastModifiedDate":"2023-09-08"},{"lineNumber":42,"author":{"gitId":"rohitcube"},"content":"        String[] words \u003d line.split(\"/by\");","lastModifiedDate":"2023-09-15"},{"lineNumber":43,"author":{"gitId":"rohitcube"},"content":"        String[] words2 \u003d line.split(\" \");","lastModifiedDate":"2023-09-15"},{"lineNumber":44,"author":{"gitId":"rohitcube"},"content":"        try {","lastModifiedDate":"2023-09-15"},{"lineNumber":45,"author":{"gitId":"rohitcube"},"content":"            String description \u003d words2[1];","lastModifiedDate":"2023-09-15"},{"lineNumber":46,"author":{"gitId":"rohitcube"},"content":"            String by \u003d words[1];","lastModifiedDate":"2023-09-15"},{"lineNumber":47,"author":{"gitId":"rohitcube"},"content":"            tasks.add(new Deadline(description, by));","lastModifiedDate":"2023-09-07"},{"lineNumber":48,"author":{"gitId":"rohitcube"},"content":"            tasks.get(tasks.size() - 1).printNewTask();","lastModifiedDate":"2023-09-08"},{"lineNumber":49,"author":{"gitId":"rohitcube"},"content":"        } catch(ArrayIndexOutOfBoundsException e) {","lastModifiedDate":"2023-09-15"},{"lineNumber":50,"author":{"gitId":"rohitcube"},"content":"            System.out.println(\"_____________________________________________________\");","lastModifiedDate":"2023-09-15"},{"lineNumber":51,"author":{"gitId":"rohitcube"},"content":"            System.out.println(DukeyException.deadlineDescriptionError());","lastModifiedDate":"2023-09-15"},{"lineNumber":52,"author":{"gitId":"rohitcube"},"content":"            System.out.println(\"_____________________________________________________\");","lastModifiedDate":"2023-09-15"},{"lineNumber":53,"author":{"gitId":"rohitcube"},"content":"        }","lastModifiedDate":"2023-09-15"},{"lineNumber":54,"author":{"gitId":"rohitcube"},"content":"    }","lastModifiedDate":"2023-09-07"},{"lineNumber":55,"author":{"gitId":"rohitcube"},"content":"","lastModifiedDate":"2023-09-07"},{"lineNumber":56,"author":{"gitId":"rohitcube"},"content":"    private static void unmarkTask(String line, ArrayList\u003cTask\u003e tasks) {","lastModifiedDate":"2023-09-08"},{"lineNumber":57,"author":{"gitId":"rohitcube"},"content":"        String[] words \u003d line.split(\" \");","lastModifiedDate":"2023-09-15"},{"lineNumber":58,"author":{"gitId":"rohitcube"},"content":"        int taskNum \u003d Integer.parseInt(words[1]) - 1;","lastModifiedDate":"2023-09-15"},{"lineNumber":59,"author":{"gitId":"rohitcube"},"content":"        tasks.get(taskNum).unmarkTask();","lastModifiedDate":"2023-09-08"},{"lineNumber":60,"author":{"gitId":"rohitcube"},"content":"    }","lastModifiedDate":"2023-09-07"},{"lineNumber":61,"author":{"gitId":"rohitcube"},"content":"","lastModifiedDate":"2023-09-07"},{"lineNumber":62,"author":{"gitId":"rohitcube"},"content":"    private static void markTask(String line, ArrayList\u003cTask\u003e tasks) {","lastModifiedDate":"2023-09-08"},{"lineNumber":63,"author":{"gitId":"rohitcube"},"content":"        String[] words \u003d line.split(\" \");","lastModifiedDate":"2023-09-15"},{"lineNumber":64,"author":{"gitId":"rohitcube"},"content":"        int taskNum \u003d Integer.parseInt(words[1]) - 1;","lastModifiedDate":"2023-09-15"},{"lineNumber":65,"author":{"gitId":"rohitcube"},"content":"        tasks.get(taskNum).setDone();","lastModifiedDate":"2023-09-08"},{"lineNumber":66,"author":{"gitId":"rohitcube"},"content":"    }","lastModifiedDate":"2023-09-07"},{"lineNumber":67,"author":{"gitId":"rohitcube"},"content":"","lastModifiedDate":"2023-09-07"},{"lineNumber":68,"author":{"gitId":"rohitcube"},"content":"","lastModifiedDate":"2023-09-08"},{"lineNumber":69,"author":{"gitId":"rohitcube"},"content":"    public static void printTaskList(ArrayList\u003cTask\u003e tasks) {","lastModifiedDate":"2023-09-08"},{"lineNumber":70,"author":{"gitId":"rohitcube"},"content":"        System.out.println(\"Here are the tasks in your list:\");","lastModifiedDate":"2023-09-08"},{"lineNumber":71,"author":{"gitId":"rohitcube"},"content":"        int index \u003d 1;","lastModifiedDate":"2023-09-08"},{"lineNumber":72,"author":{"gitId":"rohitcube"},"content":"        for (Task task : tasks) {","lastModifiedDate":"2023-09-08"},{"lineNumber":73,"author":{"gitId":"rohitcube"},"content":"            System.out.println((index++) + \".\" + task);","lastModifiedDate":"2023-09-08"},{"lineNumber":74,"author":{"gitId":"rohitcube"},"content":"        }","lastModifiedDate":"2023-09-07"},{"lineNumber":75,"author":{"gitId":"rohitcube"},"content":"    }","lastModifiedDate":"2023-09-07"},{"lineNumber":76,"author":{"gitId":"rohitcube"},"content":"","lastModifiedDate":"2023-09-07"},{"lineNumber":77,"author":{"gitId":"rohitcube"},"content":"    public static void main(String[] args) {","lastModifiedDate":"2023-09-08"},{"lineNumber":78,"author":{"gitId":"rohitcube"},"content":"        System.out.println(\"Hey! I\u0027m Dukey, your virtual assistant!\\nWhat can I do for you?\\n\");","lastModifiedDate":"2023-09-08"},{"lineNumber":79,"author":{"gitId":"rohitcube"},"content":"        Scanner in \u003d new Scanner(System.in);","lastModifiedDate":"2023-09-08"},{"lineNumber":80,"author":{"gitId":"rohitcube"},"content":"        String line;","lastModifiedDate":"2023-09-08"},{"lineNumber":81,"author":{"gitId":"rohitcube"},"content":"        ArrayList\u003cTask\u003e tasks \u003d new ArrayList\u003c\u003e();","lastModifiedDate":"2023-09-08"},{"lineNumber":82,"author":{"gitId":"rohitcube"},"content":"","lastModifiedDate":"2023-09-07"},{"lineNumber":83,"author":{"gitId":"rohitcube"},"content":"        while (true) {","lastModifiedDate":"2023-09-08"},{"lineNumber":84,"author":{"gitId":"rohitcube"},"content":"            line \u003d in.nextLine();","lastModifiedDate":"2023-09-08"},{"lineNumber":85,"author":{"gitId":"rohitcube"},"content":"            String[] words \u003d line.split(\" \");","lastModifiedDate":"2023-09-15"},{"lineNumber":86,"author":{"gitId":"rohitcube"},"content":"            String firstWord \u003d words[0];","lastModifiedDate":"2023-09-15"},{"lineNumber":87,"author":{"gitId":"rohitcube"},"content":"            switch (firstWord) {","lastModifiedDate":"2023-09-15"},{"lineNumber":88,"author":{"gitId":"rohitcube"},"content":"                case \"bye\":","lastModifiedDate":"2023-09-15"},{"lineNumber":89,"author":{"gitId":"rohitcube"},"content":"                    System.out.println(\"Bye. Hope to see you again soon!\\n\");","lastModifiedDate":"2023-09-08"},{"lineNumber":90,"author":{"gitId":"rohitcube"},"content":"                    return;","lastModifiedDate":"2023-09-08"},{"lineNumber":91,"author":{"gitId":"rohitcube"},"content":"                case \"list\":","lastModifiedDate":"2023-09-15"},{"lineNumber":92,"author":{"gitId":"rohitcube"},"content":"                    printTaskList(tasks);","lastModifiedDate":"2023-09-08"},{"lineNumber":93,"author":{"gitId":"rohitcube"},"content":"                    break;","lastModifiedDate":"2023-09-15"},{"lineNumber":94,"author":{"gitId":"rohitcube"},"content":"                case \"mark\":","lastModifiedDate":"2023-09-15"},{"lineNumber":95,"author":{"gitId":"rohitcube"},"content":"                    markTask(line, tasks);","lastModifiedDate":"2023-09-08"},{"lineNumber":96,"author":{"gitId":"rohitcube"},"content":"                    break;","lastModifiedDate":"2023-09-15"},{"lineNumber":97,"author":{"gitId":"rohitcube"},"content":"                case \"unmark\":","lastModifiedDate":"2023-09-15"},{"lineNumber":98,"author":{"gitId":"rohitcube"},"content":"                    unmarkTask(line, tasks);","lastModifiedDate":"2023-09-08"},{"lineNumber":99,"author":{"gitId":"rohitcube"},"content":"                    break;","lastModifiedDate":"2023-09-15"},{"lineNumber":100,"author":{"gitId":"rohitcube"},"content":"                case \"deadline\":","lastModifiedDate":"2023-09-15"},{"lineNumber":101,"author":{"gitId":"rohitcube"},"content":"                    addDeadline(line, tasks);","lastModifiedDate":"2023-09-08"},{"lineNumber":102,"author":{"gitId":"rohitcube"},"content":"                    break;","lastModifiedDate":"2023-09-15"},{"lineNumber":103,"author":{"gitId":"rohitcube"},"content":"                case \"event\":","lastModifiedDate":"2023-09-15"},{"lineNumber":104,"author":{"gitId":"rohitcube"},"content":"                    addEvent(line, tasks);","lastModifiedDate":"2023-09-08"},{"lineNumber":105,"author":{"gitId":"rohitcube"},"content":"                    break;","lastModifiedDate":"2023-09-15"},{"lineNumber":106,"author":{"gitId":"rohitcube"},"content":"                case \"todo\":","lastModifiedDate":"2023-09-15"},{"lineNumber":107,"author":{"gitId":"rohitcube"},"content":"                    addTodo(line, tasks);","lastModifiedDate":"2023-09-08"},{"lineNumber":108,"author":{"gitId":"rohitcube"},"content":"                    break;","lastModifiedDate":"2023-09-15"},{"lineNumber":109,"author":{"gitId":"rohitcube"},"content":"                default:","lastModifiedDate":"2023-09-15"},{"lineNumber":110,"author":{"gitId":"rohitcube"},"content":"                    if (line.trim().isEmpty()) {","lastModifiedDate":"2023-09-15"},{"lineNumber":111,"author":{"gitId":"rohitcube"},"content":"                        System.out.println(\"________________________________\");","lastModifiedDate":"2023-09-15"},{"lineNumber":112,"author":{"gitId":"rohitcube"},"content":"                        System.out.println(DukeyException.EmptyInputError());","lastModifiedDate":"2023-09-15"},{"lineNumber":113,"author":{"gitId":"rohitcube"},"content":"                        System.out.println(\"________________________________\");","lastModifiedDate":"2023-09-15"},{"lineNumber":114,"author":{"gitId":"rohitcube"},"content":"                    } else {","lastModifiedDate":"2023-09-15"},{"lineNumber":115,"author":{"gitId":"rohitcube"},"content":"                        System.out.println(\"____________________________________________________________\");","lastModifiedDate":"2023-09-15"},{"lineNumber":116,"author":{"gitId":"rohitcube"},"content":"                        System.out.println(DukeyException.InvalidInputError());","lastModifiedDate":"2023-09-15"},{"lineNumber":117,"author":{"gitId":"rohitcube"},"content":"                        System.out.println(\"____________________________________________________________\");","lastModifiedDate":"2023-09-15"},{"lineNumber":118,"author":{"gitId":"rohitcube"},"content":"                    }","lastModifiedDate":"2023-09-15"},{"lineNumber":119,"author":{"gitId":"rohitcube"},"content":"","lastModifiedDate":"2023-09-15"},{"lineNumber":120,"author":{"gitId":"rohitcube"},"content":"            }","lastModifiedDate":"2023-09-07"},{"lineNumber":121,"author":{"gitId":"rohitcube"},"content":"        }","lastModifiedDate":"2023-09-07"},{"lineNumber":122,"author":{"gitId":"rohitcube"},"content":"    }","lastModifiedDate":"2023-09-07"},{"lineNumber":123,"author":{"gitId":"rohitcube"},"content":"}","lastModifiedDate":"2023-09-07"}],"authorContributionMap":{"rohitcube":123}},{"path":"src/main/java/Tasks/Deadline.java","fileType":"java","lines":[{"lineNumber":1,"author":{"gitId":"rohitcube"},"content":"package Tasks;","lastModifiedDate":"2023-09-15"},{"lineNumber":2,"author":{"gitId":"rohitcube"},"content":"","lastModifiedDate":"2023-09-15"},{"lineNumber":3,"author":{"gitId":"rohitcube"},"content":"import Tasks.Task;","lastModifiedDate":"2023-09-15"},{"lineNumber":4,"author":{"gitId":"rohitcube"},"content":"","lastModifiedDate":"2023-09-08"},{"lineNumber":5,"author":{"gitId":"rohitcube"},"content":"public class Deadline extends Task {","lastModifiedDate":"2023-09-08"},{"lineNumber":6,"author":{"gitId":"rohitcube"},"content":"    private String due;","lastModifiedDate":"2023-09-08"},{"lineNumber":7,"author":{"gitId":"rohitcube"},"content":"","lastModifiedDate":"2023-09-08"},{"lineNumber":8,"author":{"gitId":"rohitcube"},"content":"    public Deadline(String description, String due) {","lastModifiedDate":"2023-09-08"},{"lineNumber":9,"author":{"gitId":"rohitcube"},"content":"        super(description);","lastModifiedDate":"2023-09-08"},{"lineNumber":10,"author":{"gitId":"rohitcube"},"content":"        this.due \u003d due;","lastModifiedDate":"2023-09-08"},{"lineNumber":11,"author":{"gitId":"rohitcube"},"content":"        this.type \u003d \u0027D\u0027;","lastModifiedDate":"2023-09-15"},{"lineNumber":12,"author":{"gitId":"rohitcube"},"content":"    }","lastModifiedDate":"2023-09-08"},{"lineNumber":13,"author":{"gitId":"rohitcube"},"content":"    // appends \"[D]\" to the beginning of the string.","lastModifiedDate":"2023-09-08"},{"lineNumber":14,"author":{"gitId":"rohitcube"},"content":"    // Then, it calls super.toString(), ie. it calls the toString() method of the superclass","lastModifiedDate":"2023-09-08"},{"lineNumber":15,"author":{"gitId":"rohitcube"},"content":"    // then adds the due date","lastModifiedDate":"2023-09-08"},{"lineNumber":16,"author":{"gitId":"rohitcube"},"content":"    @Override","lastModifiedDate":"2023-09-08"},{"lineNumber":17,"author":{"gitId":"rohitcube"},"content":"    public String toString() {","lastModifiedDate":"2023-09-08"},{"lineNumber":18,"author":{"gitId":"rohitcube"},"content":"        return \"[\" + this.type + \"]\" + super.toString() + \" (by:\"+ this.due + \")\";","lastModifiedDate":"2023-09-15"},{"lineNumber":19,"author":{"gitId":"rohitcube"},"content":"    }","lastModifiedDate":"2023-09-08"},{"lineNumber":20,"author":{"gitId":"rohitcube"},"content":"}","lastModifiedDate":"2023-09-08"}],"authorContributionMap":{"rohitcube":20}},{"path":"src/main/java/Tasks/Event.java","fileType":"java","lines":[{"lineNumber":1,"author":{"gitId":"rohitcube"},"content":"package Tasks;","lastModifiedDate":"2023-09-15"},{"lineNumber":2,"author":{"gitId":"rohitcube"},"content":"","lastModifiedDate":"2023-09-15"},{"lineNumber":3,"author":{"gitId":"rohitcube"},"content":"import Tasks.Task;","lastModifiedDate":"2023-09-15"},{"lineNumber":4,"author":{"gitId":"rohitcube"},"content":"","lastModifiedDate":"2023-09-15"},{"lineNumber":5,"author":{"gitId":"rohitcube"},"content":"public class Event extends Task {","lastModifiedDate":"2023-09-08"},{"lineNumber":6,"author":{"gitId":"rohitcube"},"content":"    private String from;","lastModifiedDate":"2023-09-08"},{"lineNumber":7,"author":{"gitId":"rohitcube"},"content":"    private String by;","lastModifiedDate":"2023-09-08"},{"lineNumber":8,"author":{"gitId":"rohitcube"},"content":"","lastModifiedDate":"2023-09-08"},{"lineNumber":9,"author":{"gitId":"rohitcube"},"content":"    public Event(String from, String by, String description) {","lastModifiedDate":"2023-09-08"},{"lineNumber":10,"author":{"gitId":"rohitcube"},"content":"        // call by the superclass (task) constructor","lastModifiedDate":"2023-09-08"},{"lineNumber":11,"author":{"gitId":"rohitcube"},"content":"        super(description);","lastModifiedDate":"2023-09-08"},{"lineNumber":12,"author":{"gitId":"rohitcube"},"content":"        this.from \u003d from;","lastModifiedDate":"2023-09-08"},{"lineNumber":13,"author":{"gitId":"rohitcube"},"content":"        this.by \u003d by;","lastModifiedDate":"2023-09-08"},{"lineNumber":14,"author":{"gitId":"rohitcube"},"content":"        this.type \u003d \u0027E\u0027;","lastModifiedDate":"2023-09-15"},{"lineNumber":15,"author":{"gitId":"rohitcube"},"content":"    }","lastModifiedDate":"2023-09-08"},{"lineNumber":16,"author":{"gitId":"rohitcube"},"content":"    // appends \"[R]\" to the beginning of the string.","lastModifiedDate":"2023-09-08"},{"lineNumber":17,"author":{"gitId":"rohitcube"},"content":"    // Then, it calls super.toString(), ie. it calls the toString() method of the superclass","lastModifiedDate":"2023-09-08"},{"lineNumber":18,"author":{"gitId":"rohitcube"},"content":"    // then adds the from and to timings","lastModifiedDate":"2023-09-08"},{"lineNumber":19,"author":{"gitId":"rohitcube"},"content":"    @Override","lastModifiedDate":"2023-09-08"},{"lineNumber":20,"author":{"gitId":"rohitcube"},"content":"    public String toString() {","lastModifiedDate":"2023-09-08"},{"lineNumber":21,"author":{"gitId":"rohitcube"},"content":"        return \"[E]\" + super.toString() + \"(from: \" + this.from + \"to: \" + this.by + \")\";","lastModifiedDate":"2023-09-08"},{"lineNumber":22,"author":{"gitId":"rohitcube"},"content":"    }","lastModifiedDate":"2023-09-08"},{"lineNumber":23,"author":{"gitId":"rohitcube"},"content":"}","lastModifiedDate":"2023-09-08"}],"authorContributionMap":{"rohitcube":23}},{"path":"src/main/java/Tasks/Task.java","fileType":"java","lines":[{"lineNumber":1,"author":{"gitId":"rohitcube"},"content":"package Tasks;","lastModifiedDate":"2023-09-15"},{"lineNumber":2,"author":{"gitId":"rohitcube"},"content":"","lastModifiedDate":"2023-09-15"},{"lineNumber":3,"author":{"gitId":"rohitcube"},"content":"public class Task {","lastModifiedDate":"2023-09-08"},{"lineNumber":4,"author":{"gitId":"rohitcube"},"content":"    protected String description;","lastModifiedDate":"2023-09-08"},{"lineNumber":5,"author":{"gitId":"rohitcube"},"content":"    protected boolean isDone;","lastModifiedDate":"2023-09-08"},{"lineNumber":6,"author":{"gitId":"rohitcube"},"content":"","lastModifiedDate":"2023-09-15"},{"lineNumber":7,"author":{"gitId":"rohitcube"},"content":"    protected char type;","lastModifiedDate":"2023-09-15"},{"lineNumber":8,"author":{"gitId":"rohitcube"},"content":"    protected static int numTasks \u003d 0;","lastModifiedDate":"2023-09-08"},{"lineNumber":9,"author":{"gitId":"rohitcube"},"content":"","lastModifiedDate":"2023-09-08"},{"lineNumber":10,"author":{"gitId":"rohitcube"},"content":"    public String getStatusIcon() {","lastModifiedDate":"2023-09-08"},{"lineNumber":11,"author":{"gitId":"rohitcube"},"content":"        return (isDone ? \"X\" : \" \");","lastModifiedDate":"2023-09-08"},{"lineNumber":12,"author":{"gitId":"rohitcube"},"content":"    }","lastModifiedDate":"2023-09-08"},{"lineNumber":13,"author":{"gitId":"rohitcube"},"content":"    public static int getNumTasks() {","lastModifiedDate":"2023-09-08"},{"lineNumber":14,"author":{"gitId":"rohitcube"},"content":"        return numTasks;","lastModifiedDate":"2023-09-08"},{"lineNumber":15,"author":{"gitId":"rohitcube"},"content":"    }","lastModifiedDate":"2023-09-08"},{"lineNumber":16,"author":{"gitId":"rohitcube"},"content":"","lastModifiedDate":"2023-09-08"},{"lineNumber":17,"author":{"gitId":"rohitcube"},"content":"    public String getDescription() {","lastModifiedDate":"2023-09-08"},{"lineNumber":18,"author":{"gitId":"rohitcube"},"content":"        return this.description;","lastModifiedDate":"2023-09-08"},{"lineNumber":19,"author":{"gitId":"rohitcube"},"content":"    }","lastModifiedDate":"2023-09-08"},{"lineNumber":20,"author":{"gitId":"rohitcube"},"content":"","lastModifiedDate":"2023-09-08"},{"lineNumber":21,"author":{"gitId":"rohitcube"},"content":"    public boolean isDone() {","lastModifiedDate":"2023-09-15"},{"lineNumber":22,"author":{"gitId":"rohitcube"},"content":"        return this.isDone;","lastModifiedDate":"2023-09-15"},{"lineNumber":23,"author":{"gitId":"rohitcube"},"content":"    }","lastModifiedDate":"2023-09-15"},{"lineNumber":24,"author":{"gitId":"rohitcube"},"content":"","lastModifiedDate":"2023-09-15"},{"lineNumber":25,"author":{"gitId":"rohitcube"},"content":"    public void setDone() {","lastModifiedDate":"2023-09-08"},{"lineNumber":26,"author":{"gitId":"rohitcube"},"content":"        this.isDone \u003d true;","lastModifiedDate":"2023-09-08"},{"lineNumber":27,"author":{"gitId":"rohitcube"},"content":"        System.out.println(\"Nice! I\u0027ve marked this task as done:\\n\\t  \" + this);","lastModifiedDate":"2023-09-08"},{"lineNumber":28,"author":{"gitId":"rohitcube"},"content":"    }","lastModifiedDate":"2023-09-08"},{"lineNumber":29,"author":{"gitId":"rohitcube"},"content":"    // defines constructor for the task class","lastModifiedDate":"2023-09-08"},{"lineNumber":30,"author":{"gitId":"rohitcube"},"content":"    public Task(String description) {","lastModifiedDate":"2023-09-08"},{"lineNumber":31,"author":{"gitId":"rohitcube"},"content":"        this.description \u003d description;","lastModifiedDate":"2023-09-08"},{"lineNumber":32,"author":{"gitId":"rohitcube"},"content":"        this.isDone \u003d false;","lastModifiedDate":"2023-09-08"},{"lineNumber":33,"author":{"gitId":"rohitcube"},"content":"        this.type \u003d \u0027T\u0027;","lastModifiedDate":"2023-09-15"},{"lineNumber":34,"author":{"gitId":"rohitcube"},"content":"        numTasks++;","lastModifiedDate":"2023-09-08"},{"lineNumber":35,"author":{"gitId":"rohitcube"},"content":"    }","lastModifiedDate":"2023-09-08"},{"lineNumber":36,"author":{"gitId":"rohitcube"},"content":"","lastModifiedDate":"2023-09-08"},{"lineNumber":37,"author":{"gitId":"rohitcube"},"content":"    // made changes as an earlier comment mentioned it was better to have","lastModifiedDate":"2023-09-08"},{"lineNumber":38,"author":{"gitId":"rohitcube"},"content":"    // mark and unmark as two different functions","lastModifiedDate":"2023-09-08"},{"lineNumber":39,"author":{"gitId":"rohitcube"},"content":"    public void unmarkTask() {","lastModifiedDate":"2023-09-08"},{"lineNumber":40,"author":{"gitId":"rohitcube"},"content":"        this.isDone \u003d false;","lastModifiedDate":"2023-09-08"},{"lineNumber":41,"author":{"gitId":"rohitcube"},"content":"        System.out.println(\"Nice! I\u0027ve marked this task as done:\\n\\t  \" + this);","lastModifiedDate":"2023-09-08"},{"lineNumber":42,"author":{"gitId":"rohitcube"},"content":"    }","lastModifiedDate":"2023-09-08"},{"lineNumber":43,"author":{"gitId":"rohitcube"},"content":"","lastModifiedDate":"2023-09-08"},{"lineNumber":44,"author":{"gitId":"rohitcube"},"content":"    // the superclass toString outputs the mark box and the description","lastModifiedDate":"2023-09-08"},{"lineNumber":45,"author":{"gitId":"rohitcube"},"content":"    @Override","lastModifiedDate":"2023-09-08"},{"lineNumber":46,"author":{"gitId":"rohitcube"},"content":"    public String toString() {","lastModifiedDate":"2023-09-08"},{"lineNumber":47,"author":{"gitId":"rohitcube"},"content":"        return \"[\" + this.getStatusIcon() + \"] \" + this.getDescription();","lastModifiedDate":"2023-09-08"},{"lineNumber":48,"author":{"gitId":"rohitcube"},"content":"    }","lastModifiedDate":"2023-09-08"},{"lineNumber":49,"author":{"gitId":"rohitcube"},"content":"","lastModifiedDate":"2023-09-08"},{"lineNumber":50,"author":{"gitId":"rohitcube"},"content":"    //","lastModifiedDate":"2023-09-08"},{"lineNumber":51,"author":{"gitId":"rohitcube"},"content":"    public void printNewTask() {","lastModifiedDate":"2023-09-08"},{"lineNumber":52,"author":{"gitId":"rohitcube"},"content":"        System.out.print(\"Got it. I\u0027ve added this task:\\n  \" + this + \"\\nNow you have \" + getNumTasks());","lastModifiedDate":"2023-09-08"},{"lineNumber":53,"author":{"gitId":"rohitcube"},"content":"        if (getNumTasks() \u003e 1) {","lastModifiedDate":"2023-09-08"},{"lineNumber":54,"author":{"gitId":"rohitcube"},"content":"            System.out.println(\" tasks in the list.\");","lastModifiedDate":"2023-09-08"},{"lineNumber":55,"author":{"gitId":"rohitcube"},"content":"        } else {","lastModifiedDate":"2023-09-08"},{"lineNumber":56,"author":{"gitId":"rohitcube"},"content":"            System.out.println(\" task in the list.\");","lastModifiedDate":"2023-09-08"},{"lineNumber":57,"author":{"gitId":"rohitcube"},"content":"        }","lastModifiedDate":"2023-09-08"},{"lineNumber":58,"author":{"gitId":"rohitcube"},"content":"    }","lastModifiedDate":"2023-09-08"},{"lineNumber":59,"author":{"gitId":"rohitcube"},"content":"}","lastModifiedDate":"2023-09-08"}],"authorContributionMap":{"rohitcube":59}},{"path":"src/main/java/Tasks/Todo.java","fileType":"java","lines":[{"lineNumber":1,"author":{"gitId":"rohitcube"},"content":"package Tasks;","lastModifiedDate":"2023-09-15"},{"lineNumber":2,"author":{"gitId":"rohitcube"},"content":"","lastModifiedDate":"2023-09-15"},{"lineNumber":3,"author":{"gitId":"rohitcube"},"content":"import Tasks.Task;","lastModifiedDate":"2023-09-15"},{"lineNumber":4,"author":{"gitId":"rohitcube"},"content":"","lastModifiedDate":"2023-09-15"},{"lineNumber":5,"author":{"gitId":"rohitcube"},"content":"public class Todo extends Task {","lastModifiedDate":"2023-09-08"},{"lineNumber":6,"author":{"gitId":"rohitcube"},"content":"    public Todo(String description) {","lastModifiedDate":"2023-09-08"},{"lineNumber":7,"author":{"gitId":"rohitcube"},"content":"        super(description);","lastModifiedDate":"2023-09-08"},{"lineNumber":8,"author":{"gitId":"rohitcube"},"content":"    }","lastModifiedDate":"2023-09-08"},{"lineNumber":9,"author":{"gitId":"rohitcube"},"content":"    // It appends \"[T]\" to the beginning of the string.","lastModifiedDate":"2023-09-08"},{"lineNumber":10,"author":{"gitId":"rohitcube"},"content":"    //  Then, it calls super.toString(), which means it calls the toString() method of the superclass","lastModifiedDate":"2023-09-15"},{"lineNumber":11,"author":{"gitId":"rohitcube"},"content":"    @Override","lastModifiedDate":"2023-09-08"},{"lineNumber":12,"author":{"gitId":"rohitcube"},"content":"    public String toString() {","lastModifiedDate":"2023-09-08"},{"lineNumber":13,"author":{"gitId":"rohitcube"},"content":"        return \"[T]\" + super.toString();","lastModifiedDate":"2023-09-08"},{"lineNumber":14,"author":{"gitId":"rohitcube"},"content":"    }","lastModifiedDate":"2023-09-08"},{"lineNumber":15,"author":{"gitId":"rohitcube"},"content":"}","lastModifiedDate":"2023-09-08"}],"authorContributionMap":{"rohitcube":15}},{"path":"src/main/java/dukey/DukeyException.java","fileType":"java","lines":[{"lineNumber":1,"author":{"gitId":"rohitcube"},"content":"package dukey;","lastModifiedDate":"2023-09-15"},{"lineNumber":2,"author":{"gitId":"rohitcube"},"content":"","lastModifiedDate":"2023-09-15"},{"lineNumber":3,"author":{"gitId":"rohitcube"},"content":"public class DukeyException extends Exception {","lastModifiedDate":"2023-09-08"},{"lineNumber":4,"author":{"gitId":"rohitcube"},"content":"    public DukeyException(String message){","lastModifiedDate":"2023-09-15"},{"lineNumber":5,"author":{"gitId":"rohitcube"},"content":"        super(message);","lastModifiedDate":"2023-09-15"},{"lineNumber":6,"author":{"gitId":"rohitcube"},"content":"    }","lastModifiedDate":"2023-09-15"},{"lineNumber":7,"author":{"gitId":"rohitcube"},"content":"","lastModifiedDate":"2023-09-15"},{"lineNumber":8,"author":{"gitId":"rohitcube"},"content":"    public static String InvalidInputError(){","lastModifiedDate":"2023-09-15"},{"lineNumber":9,"author":{"gitId":"rohitcube"},"content":"        return \"☹ OOPS!!! I\u0027m sorry, but I don\u0027t know what that means :-(\";","lastModifiedDate":"2023-09-15"},{"lineNumber":10,"author":{"gitId":"rohitcube"},"content":"    }","lastModifiedDate":"2023-09-15"},{"lineNumber":11,"author":{"gitId":"rohitcube"},"content":"","lastModifiedDate":"2023-09-15"},{"lineNumber":12,"author":{"gitId":"rohitcube"},"content":"    public static String EmptyInputError(){","lastModifiedDate":"2023-09-15"},{"lineNumber":13,"author":{"gitId":"rohitcube"},"content":"        return \"☹ OOPS!!! I\u0027m sorry, but you have to input something :-|\";","lastModifiedDate":"2023-09-15"},{"lineNumber":14,"author":{"gitId":"rohitcube"},"content":"    }","lastModifiedDate":"2023-09-15"},{"lineNumber":15,"author":{"gitId":"rohitcube"},"content":"","lastModifiedDate":"2023-09-15"},{"lineNumber":16,"author":{"gitId":"rohitcube"},"content":"    public static String todoDescriptionError(){","lastModifiedDate":"2023-09-15"},{"lineNumber":17,"author":{"gitId":"rohitcube"},"content":"        return \"☹ OOPS!!! The description of a todo cannot be empty.\";","lastModifiedDate":"2023-09-15"},{"lineNumber":18,"author":{"gitId":"rohitcube"},"content":"    }","lastModifiedDate":"2023-09-15"},{"lineNumber":19,"author":{"gitId":"rohitcube"},"content":"","lastModifiedDate":"2023-09-15"},{"lineNumber":20,"author":{"gitId":"rohitcube"},"content":"    public static String deadlineDescriptionError(){","lastModifiedDate":"2023-09-15"},{"lineNumber":21,"author":{"gitId":"rohitcube"},"content":"        return \"☹ OOPS!!! Please enter the description then \u0027/by\u0027, followed by the time.\";","lastModifiedDate":"2023-09-15"},{"lineNumber":22,"author":{"gitId":"rohitcube"},"content":"    }","lastModifiedDate":"2023-09-15"},{"lineNumber":23,"author":{"gitId":"rohitcube"},"content":"","lastModifiedDate":"2023-09-15"},{"lineNumber":24,"author":{"gitId":"rohitcube"},"content":"    public static String EventFormatError(){","lastModifiedDate":"2023-09-15"},{"lineNumber":25,"author":{"gitId":"rohitcube"},"content":"        return \"☹ OOPS!!! Please enter \u0027/from\u0027 and \u0027/to\u0027 into your instructions.\";","lastModifiedDate":"2023-09-15"},{"lineNumber":26,"author":{"gitId":"rohitcube"},"content":"    }","lastModifiedDate":"2023-09-08"},{"lineNumber":27,"author":{"gitId":"rohitcube"},"content":"","lastModifiedDate":"2023-09-15"},{"lineNumber":28,"author":{"gitId":"rohitcube"},"content":"}","lastModifiedDate":"2023-09-08"}],"authorContributionMap":{"rohitcube":28}}]
